Workbook

Sheet Presupuesto
A1: Prueba de exportacion de datos para project
A3: Oferente:
A4: Ubicación:
A5: Fecha: | C5: 17/08/2023
A7: PRESUPUESTO
A8: Ítem | B8: Código | C8: Descripción | D8: Unidad | E8: Cantidad | F8: P.Unitario | G8: P.Total
A9: 1 | B9: 504055 | C9: Excavación manual, zanja 0-2 m, material sin clasificar | D9: m3 | E9: 1.55 | F9: 10.01 | G9: 15.52
A10: 2 | B10: 504001 | C10: Excavación a máquina con retroexcavadora | D10: m3 | E10: 2.55 | F10: 1.61 | G10: 4.11
A11: 3 | B11: 505055 | C11: Relleno compactado con material de mejoramiento cribado | D11: m3 | E11: 7.89 | F11: 28.39 | G11: 224
A12: 4 | B12: 510037 | C12: Mampostería de bloque e=15cm | D12: m2 | E12: 101.75 | F12: 15.99 | G12: 1626.98
A13: 5 | B13: 506004 | C13: Transporte de materiales hasta 6 km, incluye pago en escombrera | D13: m3 | E13: 1003.64 | F13: 1.01 | G13: 1013.68
A14: SUBTOTAL | G14: 2884.29
A15: IVA | F15: 12 % | G15: 346.11
A16: TOTAL | G16: 3230.4
A18: Son: | B18: TRES MIL DOSCIENTOS TREINTA CON 40/100 DÓLARES DE LOS ESTADOS UNIDOS DE AMÉRICA

Sheet 504055
A1: Análisis de Precios Unitarios
A3: Código: | B3: 504055
A4: Descrip.: | B4: Excavación manual, zanja 0-2 m, material sin clasificar
A5: Unidad: | B5: m3
A7: COSTOS DIRECTOS
A9: Equipo y herramienta
A10: Código | B10: Descripción | C10: Unidad | D10: Cantidad | E10: Precio | F10: Rendim. | G10: Total | H10: %
A11: 101022 | B11: Herramientas varias | C11: Hora | D11: 1 | E11: 0.5 | F11: 2 | G11: 1 | H11: 0.1118568
A12: Subtotal de Equipo: | G12: 1 | H12: 0.1118568
A14: Materiales
A15: Código | B15: Descripción | C15: Unidad | D15: Cantidad | E15: Precio | G15: Total | H15: %
A17: Subtotal de Materiales: | G17: 0 | H17: 0
A19: Transporte
A20: Código | B20: Descripción | C20: Unidad | D20: Cantidad | E20: Tarifa/U | F20: Distancia | G20: Total | H20: %
A22: Subtotal de Transporte: | G22: 0 | H22: 0
A24: Mano de Obra
A25: Código | B25: Descripción | D25: Número | E25: S.R.H. | F25: Rendim. | G25: Total | H25: %
A26: 402015 | B26: Peón | D26: 1 | E26: 3.46 | F26: 2 | G26: 6.92 | H26: 0.7740492
A27: 404006 | B27: Maestro mayor en ejecución de obras civiles | D27: 1 | E27: 5.11 | F27: 0.2 | G27: 1.02 | H27: 0.114094
A28: Subtotal de Mano de Obra: | G28: 7.94 | H28: 0.8881432
A30: Costo Directo Total: | H30: 8.94
A32: COSTOS INDIRECTOS
A33: 12 % | H33: 1.07
A35: Precio Unitario Total ................................................................................................. | H35: 10.01
A37: Son: | B37: DIEZ CON 01/100 DÓLARES DE LOS ESTADOS UNIDOS DE AMÉRICA

Sheet 504001
A1: Análisis de Precios Unitarios
A3: Código: | B3: 504001
A4: Descrip.: | B4: Excavación a máquina con retroexcavadora
A5: Unidad: | B5: m3
A7: COSTOS DIRECTOS
A9: Equipo y herramienta
A10: Código | B10: Descripción | C10: Unidad | D10: Cantidad | E10: Precio | F10: Rendim. | G10: Total | H10: %
A11: 102004 | B11: Retroexcavadora | C11: Hora | D11: 1 | E11: 20 | F11: 0.0385 | G11: 0.77 | H11: 0.5347222
A12: Subtotal de Equipo: | G12: 0.77 | H12: 0.5347222
A14: Materiales
A15: Código | B15: Descripción | C15: Unidad | D15: Cantidad | E15: Precio | G15: Total | H15: %
A17: Subtotal de Materiales: | G17: 0 | H17: 0
A19: Transporte
A20: Código | B20: Descripción | C20: Unidad | D20: Cantidad | E20: Tarifa/U | F20: Distancia | G20: Total | H20: %
A22: Subtotal de Transporte: | G22: 0 | H22: 0
A24: Mano de Obra
A25: Código | B25: Descripción | D25: Número | E25: S.R.H. | F25: Rendim. | G25: Total | H25: %
A26: 402015 | B26: Peón | D26: 2 | E26: 3.46 | F26: 0.0385 | G26: 0.27 | H26: 0.1875
A27: 403001 | B27: Albañil | D27: 1 | E27: 4.29 | F27: 0.0385 | G27: 0.17 | H27: 0.1180556
A28: 423011 | B28: Operador de retroexcavadora | D28: 1 | E28: 3.82 | F28: 0.0385 | G28: 0.15 | H28: 0.1041667
A29: 404006 | B29: Maestro mayor en ejecución de obras civiles | D29: 1 | E29: 5.11 | F29: 0.0154 | G29: 0.08 | H29: 0.0555556
A30: Subtotal de Mano de Obra: | G30: 0.67 | H30: 0.4652779
A32: Costo Directo Total: | H32: 1.44
A34: COSTOS INDIRECTOS
A35: 12 % | H35: 0.17
A37: Precio Unitario Total ................................................................................................. | H37: 1.61
A39: Son: | B39: UNO CON 61/100 DÓLARES DE LOS ESTADOS UNIDOS DE AMÉRICA

Sheet 505055
A1: Análisis de Precios Unitarios
A3: Código: | B3: 505055
A4: Descrip.: | B4: Relleno compactado con material de mejoramiento cribado
A5: Unidad: | B5: m3
A7: COSTOS DIRECTOS
A9: Equipo y herramienta
A10: Código | B10: Descripción | C10: Unidad | D10: Cantidad | E10: Precio | F10: Rendim. | G10: Total | H10: %
A11: 101022 | B11: Herramientas varias | C11: Hora | D11: 1 | E11: 0.5 | F11: 0.6 | G11: 0.3 | H11: 0.0118343
A12: 102012 | B12: Plancha vibratoria - compactadora | C12: Hora | D12: 1 | E12: 3.5 | F12: 0.6 | G12: 2.1 | H12: 0.0828402
A13: Subtotal de Equipo: | G13: 2.4 | H13: 0.0946745
A15: Materiales
A16: Código | B16: Descripción | C16: Unidad | D16: Cantidad | E16: Precio | G16: Total | H16: %
A17: 2M9036 | B17: Mejoramiento cribado puesto en obra | C17: m3 | D17: 1.31 | E17: 13.5 | G17: 17.69 | H17: 0.6978304
A18: Subtotal de Materiales: | G18: 17.69 | H18: 0.6978304
A20: Transporte
A21: Código | B21: Descripción | C21: Unidad | D21: Cantidad | E21: Tarifa/U | F21: Distancia | G21: Total | H21: %
A23: Subtotal de Transporte: | G23: 0 | H23: 0
A25: Mano de Obra
A26: Código | B26: Descripción | D26: Número | E26: S.R.H. | F26: Rendim. | G26: Total | H26: %
A27: 402015 | B27: Peón | D27: 1 | E27: 3.46 | F27: 0.6 | G27: 2.08 | H27: 0.0820513
A28: 403001 | B28: Albañil | D28: 1 | E28: 4.29 | F28: 0.6 | G28: 2.57 | H28: 0.1013807
A29: 404006 | B29: Maestro mayor en ejecución de obras civiles | D29: 1 | E29: 5.11 | F29: 0.12 | G29: 0.61 | H29: 0.0240631
A30: Subtotal de Mano de Obra: | G30: 5.26 | H30: 0.2074951
A32: Costo Directo Total: | H32: 25.35
A34: COSTOS INDIRECTOS
A35: 12 % | H35: 3.04
A37: Precio Unitario Total ................................................................................................. | H37: 28.39
A39: Son: | B39: VEINTE Y OCHO CON 39/100 DÓLARES DE LOS ESTADOS UNIDOS DE AMÉRICA

Sheet 510037
A1: Análisis de Precios Unitarios
A3: Código: | B3: 510037
A4: Descrip.: | B4: Mampostería de bloque e=15cm
A5: Unidad: | B5: m2
A7: COSTOS DIRECTOS
A9: Equipo y herramienta
A10: Código | B10: Descripción | C10: Unidad | D10: Cantidad | E10: Precio | F10: Rendim. | G10: Total | H10: %
A11: 101022 | B11: Herramientas varias | C11: Hora | D11: 1 | E11: 0.5 | F11: 0.6 | G11: 0.3 | H11: 0.0210084
A12: Subtotal de Equipo: | G12: 0.3 | H12: 0.0210084
A14: Materiales
A15: Código | B15: Descripción | C15: Unidad | D15: Cantidad | E15: Precio | G15: Total | H15: %
A16: 2M6012 | B16: Bloque de 40 × 20 × 15 cm | C16: u | D16: 13 | E16: 0.5 | G16: 6.5 | H16: 0.4551821
A17: 508003 | B17: Mortero de cemento 1:3 | C17: m3 | D17: 0.02 | E17: 110.95 | G17: 2.22 | H17: 0.1554622
A18: Subtotal de Materiales: | G18: 8.72 | H18: 0.6106443
A20: Transporte
A21: Código | B21: Descripción | C21: Unidad | D21: Cantidad | E21: Tarifa/U | F21: Distancia | G21: Total | H21: %
A23: Subtotal de Transporte: | G23: 0 | H23: 0
A25: Mano de Obra
A26: Código | B26: Descripción | D26: Número | E26: S.R.H. | F26: Rendim. | G26: Total | H26: %
A27: 402015 | B27: Peón | D27: 1 | E27: 3.46 | F27: 0.6 | G27: 2.08 | H27: 0.1456583
A28: 403001 | B28: Albañil | D28: 1 | E28: 4.29 | F28: 0.6 | G28: 2.57 | H28: 0.179972
A29: 404006 | B29: Maestro mayor en ejecución de obras civiles | D29: 1 | E29: 5.11 | F29: 0.12 | G29: 0.61 | H29: 0.0427171
A30: Subtotal de Mano de Obra: | G30: 5.26 | H30: 0.3683474
A32: Costo Directo Total: | H32: 14.28
A34: COSTOS INDIRECTOS
A35: 12 % | H35: 1.71
A37: Precio Unitario Total ................................................................................................. | H37: 15.99
A39: Son: | B39: QUINCE CON 99/100 DÓLARES DE LOS ESTADOS UNIDOS DE AMÉRICA

Sheet 508003
A1: Análisis de Precios Unitarios
A3: Código: | B3: 508003
A4: Descrip.: | B4: Mortero de cemento 1:3
A5: Unidad: | B5: m3
A7: COSTOS DIRECTOS
A9: Equipo y herramienta
A10: Código | B10: Descripción | C10: Unidad | D10: Cantidad | E10: Precio | F10: Rendim. | G10: Total | H10: %
A11: 101022 | B11: Herramientas varias | C11: Hora | D11: 2 | E11: 0.5 | F11: 0.9 | G11: 0.9 | H11: 0.0081118
A12: Subtotal de Equipo: | G12: 0.9 | H12: 0.0081118
A14: Materiales
A15: Código | B15: Descripción | C15: Unidad | D15: Cantidad | E15: Precio | G15: Total | H15: %
A16: 2JF001 | B16: Cemento Portland Tipo I | C16: saco 50 kg | D16: 10 | E16: 7.25 | G16: 72.5 | H16: 0.6534475
A17: 2M9005 | B17: Arena puesta en obra | C17: m3 | D17: 1.15 | E17: 20.5 | G17: 23.58 | H17: 0.2125282
A18: 2LY073 | B18: Agua | C18: lt | D18: 250 | E18: 0.01 | G18: 2.5 | H18: 0.0225327
A19: Subtotal de Materiales: | G19: 98.58 | H19: 0.8885084
A21: Transporte
A22: Código | B22: Descripción | C22: Unidad | D22: Cantidad | E22: Tarifa/U | F22: Distancia | G22: Total | H22: %
A24: Subtotal de Transporte: | G24: 0 | H24: 0
M25: =1.55*2 -> 3.1
A26: Mano de Obra | M26: =2.55*0.077 -> 0.19635
A27: Código | B27: Descripción | D27: Número | E27: S.R.H. | F27: Rendim. | G27: Total | H27: % | M27: =7.89*0.6 -> 4.734
A28: 402015 | B28: Peón | D28: 2 | E28: 3.46 | F28: 0.9 | G28: 6.23 | H28: 0.0561514 | K28: =0.02*2*0.9*101.75 -> 3.663 | M28: =0.6358*101.75 -> 64.69265
A29: 403001 | B29: Albañil | D29: 1 | E29: 4.29 | F29: 0.9 | G29: 3.86 | H29: 0.0347904 | K29: =0.6*1*101.75 -> 61.05
A30: 404006 | B30: Maestro mayor en ejecución de obras civiles | D30: 1 | E30: 5.11 | F30: 0.27 | G30: 1.38 | H30: 0.012438 | K30: =SUM(K28:K29) -> 64.713
A31: Subtotal de Mano de Obra: | G31: 11.47 | H31: 0.1033798
A33: Costo Directo Total: | H33: 110.95
A35: COSTOS INDIRECTOS
A36: 12 % | H36: 13.31
A38: Precio Unitario Total ................................................................................................. | H38: 124.26
A40: Son: | B40: CIENTO VEINTE Y CUATRO CON 26/100 DÓLARES DE LOS ESTADOS UNIDOS DE AMÉRICA

Sheet 506004
A1: Análisis de Precios Unitarios
A3: Código: | B3: 506004
A4: Descrip.: | B4: Transporte de materiales hasta 6 km, incluye pago en escombrera
A5: Unidad: | B5: m3
A7: COSTOS DIRECTOS
A9: Equipo y herramienta
A10: Código | B10: Descripción | C10: Unidad | D10: Cantidad | E10: Precio | F10: Rendim. | G10: Total | H10: %
A11: 102008 | B11: Volqueta 8 m3 | C11: Hora | D11: 1 | E11: 20 | F11: 0.02 | G11: 0.4 | H11: 0.4444444
A12: Subtotal de Equipo: | G12: 0.4 | H12: 0.4444444
A14: Materiales
A15: Código | B15: Descripción | C15: Unidad | D15: Cantidad | E15: Precio | G15: Total | H15: %
A16: 2LY093 | B16: Pago por concepto de disposición de materiales en escombrera | C16: m3 | D16: 1 | E16: 0.4 | G16: 0.4 | H16: 0.4444444
A17: Subtotal de Materiales: | G17: 0.4 | H17: 0.4444444
A19: Transporte
A20: Código | B20: Descripción | C20: Unidad | D20: Cantidad | E20: Tarifa/U | F20: Distancia | G20: Total | H20: %
A22: Subtotal de Transporte: | G22: 0 | H22: 0
A24: Mano de Obra
A25: Código | B25: Descripción | D25: Número | E25: S.R.H. | F25: Rendim. | G25: Total | H25: %
A26: 427011 | B26: Chofer volquetas (Estr. Oc. C1) | D26: 1 | E26: 5 | F26: 0.02 | G26: 0.1 | H26: 0.1111111
A27: Subtotal de Mano de Obra: | G27: 0.1 | H27: 0.1111111
A29: Costo Directo Total: | H29: 0.9
A31: COSTOS INDIRECTOS
A32: 12 % | H32: 0.11
A34: Precio Unitario Total ................................................................................................. | H34: 1.01
A36: Son: | B36: UNO CON 01/100 DÓLARES DE LOS ESTADOS UNIDOS DE AMÉRICA

Sheet Agrupación de Recursos
A1: AGRUPACIÓN DE RECURSOS Y CÁLCULO DE PORCENTAJES DE INCIDENCIA
A2: Símbolo Agrup. | B2: Subcategoría | C2: Descripción del Recurso | D2: Unidad | E2: Precio | F2: Cantidad | G2: Costo Directo | H2: % Incidencia
A3: Categoría 1: Equipos y Herramientas | G3: =SUM(G4:G7) -> 456.26 | H3: =ROUND(G3/$G$31,5) -> 0.17726
A4: E | C4: Herramientas varias | D4: Hora | E4: 0.5 | F4: =ROUND((Presupuesto!E9*'504055'!D11*'504055'!F11)+(Presupuesto!E11*'505055'!D11*'505055'!F11)+(Presupuesto!E12*'510037'!D11*'510037'!F11)+(Presupuesto!E12*'508003'!D11*'508003'!F11*'510037'!D17),4) -> 72.547 | G4: =ROUND(E4*F4,2) -> 36.27 | H4: =ROUND(G4/$G$31,5) -> 0.01409
A5: E | C5: Retroexcavadora | D5: Hora | E5: 20 | F5: =ROUND('504001'!D11*'504001'!F11*Presupuesto!E10,4) -> 0.0982 | G5: =ROUND(E5*F5,2) -> 1.96 | H5: =ROUND(G5/$G$31,5) -> 0.00076
A6: E | C6: Volqueta 8m3 | D6: Hora | E6: 20 | F6: =ROUND('506004'!D11*'506004'!F11*Presupuesto!E13,4) -> 20.0728 | G6: =ROUND(E6*F6,2) -> 401.46 | H6: =ROUND(G6/$G$31,5) -> 0.15597
A7: E | C7: Plancha vibratoria - compactadora | D7: Hora | E7: 3.5 | F7: =ROUND(Presupuesto!E11*'505055'!D12*'505055'!F12,4) -> 4.734 | G7: =ROUND(E7*F7,2) -> 16.57 | H7: =ROUND(G7/$G$31,5) -> 0.00644
A8: Categoría 2: Materiales | G8: =SUM(G9:G14) -> 1402.98 | H8: =ROUND(G8/$G$31,5) -> 0.54506
A9: D | C9: Cemento Portland Tipo 1 | D9: saco 50kg | E9: 7.25 | F9: =ROUND('508003'!D16*'510037'!D17*Presupuesto!E12,4) -> 20.35 | G9: =ROUND(E9*F9,2) -> 147.54 | H9: =ROUND(G9/$G$31,5) -> 0.05732
A10: X | C10: Agua | D10: l | E10: 0.01 | F10: =ROUND('508003'!D18*'510037'!D17*Presupuesto!E12,4) -> 508.75 | G10: =ROUND(E10*F10,2) -> 5.09 | H10: =ROUND(G10/$G$31,5) -> 0.00198
A11: X | C11: Pago por concepto de disposición de materiales en escombrera | D11: m3 | E11: 0.4 | F11: =ROUND('506004'!D16*Presupuesto!E13,4) -> 1003.64 | G11: =ROUND(E11*F11,2) -> 401.46 | H11: =ROUND(G11/$G$31,5) -> 0.15597
A12: M | C12: Bloque de 40x20x15cm | D12: u | E12: 0.5 | F12: =ROUND(Presupuesto!E12*'510037'!D16,4) -> 1322.75 | G12: =ROUND(E12*F12,2) -> 661.38 | H12: =ROUND(G12/$G$31,5) -> 0.25695
A13: P | C13: Arena Puesta en Obra | D13: m3 | E13: 20.5 | F13: =ROUND('508003'!D17*'510037'!D17*Presupuesto!E12,4) -> 2.3403 | G13: =ROUND(E13*F13,2) -> 47.98 | H13: =ROUND(G13/$G$31,5) -> 0.01864
A14: P | C14: Mejoramiento cribado puesto en obra | D14: m3 | E14: 13.5 | F14: =ROUND(Presupuesto!E11*'505055'!D17,4) -> 10.3359 | G14: =ROUND(E14*F14,2) -> 139.53 | H14: =ROUND(G14/$G$31,5) -> 0.05421
A15: Categoría 3: Transporte | G15: =SUM(G16:G19) -> 0 | H15: =ROUND(G15/$G$31,5) -> 0
A20: Categoría 4: Mano de Obra | G20: =SUM(G21:G25) -> 714.73 | H20: =ROUND(G20/$G$31,5) -> 0.27768
A21: B | C21: Peón | D21: Hora | E21: 3.46 | F21: =ROUND(Presupuesto!E9*'504055'!D26*'504055'!F26+Presupuesto!E10*'504001'!D26*'504001'!F26+Presupuesto!E11*'505055'!D27*'505055'!F27+Presupuesto!E12*'510037'!D27*'510037'!F27+Presupuesto!E12*'510037'!D17*'508003'!D28*'508003'!F28,4) -> 72.7434 | G21: =ROUND(E21*F21,2) -> 251.69 | H21: =ROUND(G21/$G$31,5) -> 0.09778
A22: B | C22: Albañil | D22: Hora | E22: 4.29 | F22: =ROUND(Presupuesto!E10*'504001'!D27*'504001'!F27+Presupuesto!E11*'505055'!D28*'505055'!F28+Presupuesto!E12*'510037'!D28*'510037'!F28+Presupuesto!E12*'510037'!D17*'508003'!D29*'508003'!F29,4) -> 67.7137 | G22: =ROUND(E22*F22,2) -> 290.49 | H22: =ROUND(G22/$G$31,5) -> 0.11286
A23: B | C23: Maestro Mayor | D23: Hora | E23: 5.11 | F23: =ROUND(Presupuesto!E9*'504055'!D27*'504055'!F27+Presupuesto!E10*'504001'!D29*'504001'!F29+Presupuesto!E11*'505055'!D29*'505055'!F29+Presupuesto!E12*'510037'!D29*'510037'!F29+Presupuesto!E12*'510037'!D17*'508003'!D30*'508003'!F30,4) -> 14.0555 | G23: =ROUND(E23*F23,2) -> 71.82 | H23: =ROUND(G23/$G$31,5) -> 0.0279
A24: B | C24: Operador de retroexcavadora | D24: Hora | E24: 3.8 | F24: =ROUND(Presupuesto!E10*'504001'!D28*'504001'!F28,4) -> 0.0982 | G24: =ROUND(E24*F24,2) -> 0.37 | H24: =ROUND(G24/$G$31,5) -> 0.00014
A25: B | C25: Chofer volquetas | D25: Hora | E25: 5 | F25: =ROUND(Presupuesto!E13*'506004'!D26*'506004'!F26,4) -> 20.0728 | G25: =ROUND(E25*F25,2) -> 100.36 | H25: =ROUND(G25/$G$31,5) -> 0.03899
A26: Categoría 5: Seguridad Industrial | G26: =SUM(G27:G30) -> 0 | H26: =ROUND(G26/$G$31,5) -> 0
A31: TOTALES | G31: =+G3+G8+G15+G20+G26 -> 2573.97 | H31: =ROUND(G31/$G$31,5) -> 1
A33: Pr = Po(p1B1/B0+p2C1/C0+p3D1/D0+p4E1/E0… pnZ1/Z0 + pxX1/X0) • Pr = Valor reajustado del anticipo o de la planilla. • Po = Valor del anticipo o de la planilla calculada con las cantidades de obra ejecutada a los precios unitarios contractuales descontada la parte proporcional del anticipo, de haberlo pagado. • p1 = Coeficiente del componente mano de obra. • p2, p3, p4… pn = Coeficiente de los demás componentes principales. • px = Coeficiente de los otros componentes, considerados como “no principales”, cuyo valor no excederá de 0,200 lo que equivale al 20% de incidencia del costo directo. Los coeficientes de la fórmula se expresan y aplican al milésimo y la suma de aquellos debe ser igual a la unidad. • B0 = Sueldos y salarios mínimos de una cuadrilla tipo, más remuneraciones adicionales y obligaciones patronales; esta cuadrilla tipo estará conformada en base a los análisis de precios unitarios de la oferta adjudicada, vigentes treinta días antes de la fecha de cierre para la presentación de las ofertas. • B1 = …; esta cuadrilla tipo estará conformada sobre la base de los análisis de precios unitarios de la oferta adjudicada, vigente a la fecha de pago del anticipo o de las planillas de ejecución de obra. • C0, D0, E0,…Z0 = Los precios o índices de precios de los componentes principales vigentes treinta días antes de la fecha de cierre para la presentación de las ofertas, fecha que constará en el contrato. • C1, D1, E1,…Z1 = Los precios o los índices de precios de los componentes principales a la fecha de pago del anticipo o de las planillas de ejecución de obras. • X0 = Índice de componentes no principales correspondiente al tipo de obra y a la falta de éste, el índice de precios al consumidor treinta días antes de la fecha de cierre de la presentación de las ofertas. • X1 = Índice de componentes no principales correspondiente al tipo de obra y a falta de éste, el índice de precios al consumidor a la fecha de pago del anticipo o de las planillas de ejecución de obras. Bajo la normativa ecuatoriana, la conformación de los monomios o llamados también términos de la fórmula, no podrá exceder de 11 términos incluido el término X de saldos o varios el mismo que puede agrupar a recursos de diversa naturaleza, el resto de los términos deben agrupar recursos de similar naturaleza según la agrupación de los índices de precios del Instituto Nacional de Estadísticas y Censos (INEC) del Ecuador.

Sheet Desglose Equipo y Transporte
A1: Parámetros del Mecánico de Mantenimiento
A2: Subcategoría: | B2: ESTRUCTURA OCUPACIONAL C1 (Grupo I)
A3: Salario Hora Mínimo (SHM): | B3: 3.66
A4: Salario Hora Real (SHR): | B4: 3.8
A5: Cantidad (h-H): | B5: =+D10/B4 -> 12.006842
A7: DESGLOSE DEL EQUIPO Y TRANSPORTE
A8: Símbolo Agrup. | B8: Descripción del Recurso | C8: % Incidencia | D8: Costo Directo
A9: Categoría 1: Equipos y Herramientas | D9: =SUM('Agrupación de Recursos'!G4:G7) -> 456.26
A10: B | B10: Mecánico de Mantenimiento | C10: 0.1 | D10: =+C10*$D$9 -> 45.626
A11: C | B11: Combustibles | C11: 0.1 | D11: =+C11*$D$9 -> 45.626
A12: E | B12: Equipos | C12: 0.7 | D12: =+C12*$D$9 -> 319.382
A13: R | B13: Repuestos | C13: 0.1 | D13: =+C13*$D$9 -> 45.626
A14: X | B14: Varios | C14: 0 | D14: =+C14*$D$9 -> 0

Sheet Indices y Coeficientes
A1: ASIGNACIÓN DE ÍNDICES Y CÁLCULO DE COEFICIENTES DE LA FÓRMULA POLINÓMICA
A2: Símbolo Agrup. | B2: Índice | C2: Descripción | D2: Costo Directo | E2: Coeficiente
A3: B | B3: 0 | C3: Cuadrilla Tipo (incluye Mecánico de Mantenimiento) | D3: =+'Agrupación de Recursos'!G21+'Agrupación de Recursos'!G22+'Agrupación de Recursos'!G23+'Agrupación de Recursos'!G24+'Agrupación de Recursos'!G25+'Desglose Equipo y Transporte'!D10 -> 760.356 | E3: =ROUND(D3/$D$11,3) -> 0.295
A4: =+'Desglose Equipo y Transporte'!A11 -> C | B4: 28 | C4: Combustibles (O) | D4: =+'Desglose Equipo y Transporte'!D11 -> 45.626 | E4: =ROUND(D4/$D$11,3) -> 0.018
A5: D | B5: 23 | C5: Cemento Portland - Tipo I - Sacos | D5: =+'Agrupación de Recursos'!G9 -> 147.54 | E5: =ROUND(D5/$D$11,3) -> 0.057
A6: E | B6: 37 | C6: Equipo y maquinaria de Construc. Vial | D6: =+'Desglose Equipo y Transporte'!D12 -> 319.382 | E6: =ROUND(D6/$D$11,3) -> 0.124
A7: M | B7: 53 | C7: Madera aserrada, cepillada y/o escuadrada (preparada) | D7: =+'Agrupación de Recursos'!G12 -> 661.38 | E7: =ROUND(D7/$D$11,3) -> 0.257
A8: P | B8: 304 | C8: Materiales pétreos (Azuay) | D8: =+'Agrupación de Recursos'!G13+'Agrupación de Recursos'!G14 -> 187.51 | E8: =ROUND(D8/$D$11,3) -> 0.073
A9: =+'Desglose Equipo y Transporte'!A13 -> R | B9: 83 | C9: Repuestos para maquinaria de construcción | D9: =+'Desglose Equipo y Transporte'!D13 -> 45.626 | E9: =ROUND(D9/$D$11,3) -> 0.018
A10: X | B10: 822 | C10: Indice de Precios al Consumidor Urbano - Cuenca | D10: =+'Agrupación de Recursos'!G10+'Agrupación de Recursos'!G11+'Desglose Equipo y Transporte'!D14 -> 406.55 | E10: =ROUND(D10/$D$11,3) -> 0.158
A11: TOTALES | D11: =SUM(D3:D10) -> 2573.97 | E11: =ROUND(D11/$D$11,3) -> 1
A13: Pr = Po(p1B1/B0+p2C1/C0+p3D1/D0+p4E1/E0… pnZ1/Z0 + pxX1/X0) • Pr = Valor reajustado del anticipo o de la planilla. • Po = Valor del anticipo o de la planilla calculada con las cantidades de obra ejecutada a los precios unitarios contractuales descontada la parte proporcional del anticipo, de haberlo pagado. • p1 = Coeficiente del componente mano de obra. • p2, p3, p4… pn = Coeficiente de los demás componentes principales. • px = Coeficiente de los otros componentes, considerados como “no principales”, cuyo valor no excederá de 0,200 lo que equivale al 20% de incidencia del costo directo. Los coeficientes de la fórmula se expresan y aplican al milésimo y la suma de aquellos debe ser igual a la unidad. • B0 = Sueldos y salarios mínimos de una cuadrilla tipo, más remuneraciones adicionales y obligaciones patronales; esta cuadrilla tipo estará conformada en base a los análisis de precios unitarios de la oferta adjudicada, vigentes treinta días antes de la fecha de cierre para la presentación de las ofertas. • B1 = …; esta cuadrilla tipo estará conformada sobre la base de los análisis de precios unitarios de la oferta adjudicada, vigente a la fecha de pago del anticipo o de las planillas de ejecución de obra. • C0, D0, E0,…Z0 = Los precios o índices de precios de los componentes principales vigentes treinta días antes de la fecha de cierre para la presentación de las ofertas, fecha que constará en el contrato. • C1, D1, E1,…Z1 = Los precios o los índices de precios de los componentes principales a la fecha de pago del anticipo o de las planillas de ejecución de obras. • X0 = Índice de componentes no principales correspondiente al tipo de obra y a la falta de éste, el índice de precios al consumidor treinta días antes de la fecha de cierre de la presentación de las ofertas. • X1 = Índice de componentes no principales correspondiente al tipo de obra y a falta de éste, el índice de precios al consumidor a la fecha de pago del anticipo o de las planillas de ejecución de obras. Bajo la normativa ecuatoriana, la conformación de los monomios o llamados también términos de la fórmula, no podrá exceder de 11 términos incluido el término X de saldos o varios el mismo que puede agrupar a recursos de diversa naturaleza, el resto de los términos deben agrupar recursos de similar naturaleza según la agrupación de los índices de precios del Instituto Nacional de Estadísticas y Censos (INEC) del Ecuador.

Sheet Cuadrilla Tipo
A1: ASIGNACIÓN DE ÍNDICES Y CÁLCULO DE COEFICIENTES DE LA CUADRILLA TIPO
A2: Símbolo Agrup. | B2: Índice | C2: Descripción | D2: Subcategoría | E2: Salario Hora Mínimo (SHM) | F2: Salario Hora Real (SHR) | G2: Trabajo (h-H) | H2: Costo Directo | I2: Coeficiente
A3: B | B3: 1010 | C3: ESTRUCTURA OCUPACIONAL E2 | D3: ESTRUCTURA OCUPACIONAL E2 | E3: 3.26 | F3: 3.46 | G3: =+'Agrupación de Recursos'!F21 -> 72.7434 | H3: =+'Agrupación de Recursos'!G21 -> 251.69 | I3: =ROUND(H3/$H$8,4) -> 0.331
A4: B | B4: 1020 | C4: ESTRUCTURA OCUPACIONAL D2 | D4: ESTRUCTURA OCUPACIONAL D2 | E4: 3.3 | F4: 4.29 | G4: =+'Agrupación de Recursos'!F22 -> 67.7137 | H4: =+'Agrupación de Recursos'!G22 -> 290.49 | I4: =ROUND(H4/$H$8,4) -> 0.382
A5: B | B5: 1030 | C5: ESTRUCTURA OCUPACIONAL C1 | D5: ESTRUCTURA OCUPACIONAL C1 | E5: 3.66 | F5: 5.11 | G5: =+'Agrupación de Recursos'!F23 -> 14.0555 | H5: =+'Agrupación de Recursos'!G23 -> 71.82 | I5: =ROUND(H5/$H$8,4) -> 0.0945
A6: B | B6: 1030 | C6: ESTRUCTURA OCUPACIONAL C1 | D6: ESTRUCTURA OCUPACIONAL C1 (Grupo I) | E6: 3.66 | F6: 3.8 | G6: =+'Agrupación de Recursos'!F24+'Desglose Equipo y Transporte'!B5 -> 12.105042 | H6: =+'Agrupación de Recursos'!G24+'Desglose Equipo y Transporte'!D10 -> 45.996 | I6: =ROUND(H6/$H$8,4) -> 0.0605
A7: B | B7: 1145 | C7: CHOFERES - (Estr.Op C1) | D7: CHOFERES - (Estr.Op C1) | E7: 4.79 | F7: 5 | G7: =+'Agrupación de Recursos'!F25 -> 20.0728 | H7: =+'Agrupación de Recursos'!G25 -> 100.36 | I7: =ROUND(H7/$H$8,4) -> 0.132
A8: TOTALES | G8: =SUM(G3:G7) -> 186.69044 | H8: =SUM(H3:H7) -> 760.356 | I8: =SUM(I3:I7) -> 1
A10: Pr = Po(p1B1/B0+p2C1/C0+p3D1/D0+p4E1/E0… pnZ1/Z0 + pxX1/X0) • Pr = Valor reajustado del anticipo o de la planilla. • Po = Valor del anticipo o de la planilla calculada con las cantidades de obra ejecutada a los precios unitarios contractuales descontada la parte proporcional del anticipo, de haberlo pagado. • p1 = Coeficiente del componente mano de obra. • p2, p3, p4… pn = Coeficiente de los demás componentes principales. • px = Coeficiente de los otros componentes, considerados como “no principales”, cuyo valor no excederá de 0,200 lo que equivale al 20% de incidencia del costo directo. Los coeficientes de la fórmula se expresan y aplican al milésimo y la suma de aquellos debe ser igual a la unidad. • B0 = Sueldos y salarios mínimos de una cuadrilla tipo, más remuneraciones adicionales y obligaciones patronales; esta cuadrilla tipo estará conformada en base a los análisis de precios unitarios de la oferta adjudicada, vigentes treinta días antes de la fecha de cierre para la presentación de las ofertas. • B1 = …; esta cuadrilla tipo estará conformada sobre la base de los análisis de precios unitarios de la oferta adjudicada, vigente a la fecha de pago del anticipo o de las planillas de ejecución de obra. • C0, D0, E0,…Z0 = Los precios o índices de precios de los componentes principales vigentes treinta días antes de la fecha de cierre para la presentación de las ofertas, fecha que constará en el contrato. • C1, D1, E1,…Z1 = Los precios o los índices de precios de los componentes principales a la fecha de pago del anticipo o de las planillas de ejecución de obras. • X0 = Índice de componentes no principales correspondiente al tipo de obra y a la falta de éste, el índice de precios al consumidor treinta días antes de la fecha de cierre de la presentación de las ofertas. • X1 = Índice de componentes no principales correspondiente al tipo de obra y a falta de éste, el índice de precios al consumidor a la fecha de pago del anticipo o de las planillas de ejecución de obras. Bajo la normativa ecuatoriana, la conformación de los monomios o llamados también términos de la fórmula, no podrá exceder de 11 términos incluido el término X de saldos o varios el mismo que puede agrupar a recursos de diversa naturaleza, el resto de los términos deben agrupar recursos de similar naturaleza según la agrupación de los índices de precios del Instituto Nacional de Estadísticas y Censos (INEC) del Ecuador.

Sheet Resumen
A1: FÓRMULA POLINÓMICA
A3: Símbolo Agrup. | B3: Índice | C3: Descripción | G3: Costo Directo | H3: Coeficiente
A4: =+'Indices y Coeficientes'!A3 -> B | B4: =+'Indices y Coeficientes'!B3 -> 0 | C4: =+'Indices y Coeficientes'!C3 -> Cuadrilla Tipo (incluye Mecánico de Mantenimiento) | G4: =+'Indices y Coeficientes'!D3 -> 760.356 | H4: =+'Indices y Coeficientes'!E3 -> 0.295
A5: =+'Indices y Coeficientes'!A4 -> C | B5: =+'Indices y Coeficientes'!B4 -> 28 | C5: =+'Indices y Coeficientes'!C4 -> Combustibles (O) | G5: =+'Indices y Coeficientes'!D4 -> 45.626 | H5: =+'Indices y Coeficientes'!E4 -> 0.018
A6: =+'Indices y Coeficientes'!A5 -> D | B6: =+'Indices y Coeficientes'!B5 -> 23 | C6: =+'Indices y Coeficientes'!C5 -> Cemento Portland - Tipo I - Sacos | G6: =+'Indices y Coeficientes'!D5 -> 147.54 | H6: =+'Indices y Coeficientes'!E5 -> 0.057
A7: =+'Indices y Coeficientes'!A6 -> E | B7: =+'Indices y Coeficientes'!B6 -> 37 | C7: =+'Indices y Coeficientes'!C6 -> Equipo y maquinaria de Construc. Vial | G7: =+'Indices y Coeficientes'!D6 -> 319.382 | H7: =+'Indices y Coeficientes'!E6 -> 0.124
A8: =+'Indices y Coeficientes'!A7 -> M | B8: =+'Indices y Coeficientes'!B7 -> 53 | C8: =+'Indices y Coeficientes'!C7 -> Madera aserrada, cepillada y/o escuadrada (preparada) | G8: =+'Indices y Coeficientes'!D7 -> 661.38 | H8: =+'Indices y Coeficientes'!E7 -> 0.257
A9: =+'Indices y Coeficientes'!A8 -> P | B9: =+'Indices y Coeficientes'!B8 -> 304 | C9: =+'Indices y Coeficientes'!C8 -> Materiales pétreos (Azuay) | G9: =+'Indices y Coeficientes'!D8 -> 187.51 | H9: =+'Indices y Coeficientes'!E8 -> 0.073
A10: =+'Indices y Coeficientes'!A9 -> R | B10: =+'Indices y Coeficientes'!B9 -> 83 | C10: =+'Indices y Coeficientes'!C9 -> Repuestos para maquinaria de construcción | G10: =+'Indices y Coeficientes'!D9 -> 45.626 | H10: =+'Indices y Coeficientes'!E9 -> 0.018
A11: =+'Indices y Coeficientes'!A10 -> X | B11: =+'Indices y Coeficientes'!B10 -> 822 | C11: =+'Indices y Coeficientes'!C10 -> Indice de Precios al Consumidor Urbano - Cuenca | G11: =+'Indices y Coeficientes'!D10 -> 406.55 | H11: =+'Indices y Coeficientes'!E10 -> 0.158
A12: TOTALES | G12: =SUM(G4:G11) -> 2573.97 | H12: =SUM(H4:H11) -> 1
A14: PR = P0 (0,278B1/B0 + 0,057D1/D0 + 0,177E1/E0 + 0,257M1/M0 + 0,073P1/P0 + 0,158X1/X0)
A16: FÓRMULA DE LA CUADRILLA TIPO
A18: Símbolo Agrup. | B18: Índice | C18: Descripción | D18: SHM | E18: SHR | F18: Trabajo (h-H) | G18: Costo Directo | H18: Coeficiente
A19: B | B19: 1010 | C19: ESTRUCTURA OCUPACIONAL E2 | D19: 3.26 | E19: 3.46 | F19: =+'Cuadrilla Tipo'!G3 -> 72.7434 | G19: =+'Cuadrilla Tipo'!H3 -> 251.69 | H19: =+'Cuadrilla Tipo'!I3 -> 0.331
A20: B | B20: 1020 | C20: ESTRUCTURA OCUPACIONAL D2 | D20: 3.3 | E20: 4.29 | F20: =+'Cuadrilla Tipo'!G4 -> 67.7137 | G20: =+'Cuadrilla Tipo'!H4 -> 290.49 | H20: =+'Cuadrilla Tipo'!I4 -> 0.382
A21: B | B21: 1030 | C21: ESTRUCTURA OCUPACIONAL C1 | D21: 3.66 | E21: 5.11 | F21: =+'Cuadrilla Tipo'!G5 -> 14.0555 | G21: =+'Cuadrilla Tipo'!H5 -> 71.82 | H21: =+'Cuadrilla Tipo'!I5 -> 0.0945
A22: B | B22: 1030 | C22: ESTRUCTURA OCUPACIONAL C1 | D22: 3.66 | E22: 3.8 | F22: =+'Cuadrilla Tipo'!G6 -> 12.105042 | G22: =+'Cuadrilla Tipo'!H6 -> 45.996 | H22: =+'Cuadrilla Tipo'!I6 -> 0.0605
A23: B | B23: 1145 | C23: CHOFERES - (Estr.Op C1) | D23: 4.79 | E23: 5 | F23: =+'Cuadrilla Tipo'!G7 -> 20.0728 | G23: =+'Cuadrilla Tipo'!H7 -> 100.36 | H23: =+'Cuadrilla Tipo'!I7 -> 0.132
A24: TOTALES | F24: =SUM(F19:F23) -> 186.69044 | G24: =SUM(G19:G23) -> 760.356 | H24: =SUM(H19:H23) -> 1
A26: Bi = 0.352 (SHR ESTRUCTURA OCUPACIONAL E2)i + 0.406 (SHR ESTRUCTURA OCUPACIONAL D2)i + 0.101 (SHR ESTRUCTURA OCUPACIONAL C1)i + 0.001 (SHR ESTRUCTURA OCUPACIONAL C1)i + 0.140 (SHR CHOFERES - (Estr.Op C1))i
