Workbook

Sheet Hoja1
A2: Item | B2: Descripción | C2: Unidad | D2: Cantidad | E2: P.Unitario | H2: P.Total | I2: EQUIPO / HERRAMIENTA | K2: MANO DE OBRA | Q2: TRABAJO TOTAL | R2: UNIDADES DE RECURSOS ASUMIDOS TOTALES | S2: Duración (horas) | T2: Jornada Laboral (horas) | U2: Dias útiles | V2: Factor de Conversión (Días Mes / Días Laborables Mensual) | W2: Dias Calendario
E3: Costo Directo | F3: Costo Indirecto | G3: P. Unitario | I3: Rendimiento Unitario Total (h/u) | J3: Trabajo (h-EH) | K3: Rendimiento Unitario Total (h/u) | L3: Producción Total (u/h) | M3: Numero de Hombres en Cuadrilla (H) | N3: Productividad (u/h-H) | O3: Rendimiento Global Actividad (h-H/u) | P3: Trabajo (h-H)
A4: 1 | B4: =+'1'!$B$1 -> Excavación manual, zanja 0-2 m, material sin clasificar | C4: =+'1'!$I$1 -> m3 | D4: 1.55 | E4: =+'1'!$G$35 -> 8.94 | F4: =+'1'!$G$36 -> 1.07 | G4: =+E4+F4 -> 10.01 | H4: =+D4*G4 -> 15.5155 | I4: =+'1'!$F$10 -> 0 | J4: =ROUND('1'!$I$10*Hoja1!D4,2) -> 3.1 | K4: =+'1'!F26 -> 0 | L4: =1/K4 -> #DIV/0! | M4: =+'1'!$D$26 -> 2 | N4: =+L4/M4 -> #DIV/0! | O4: =1/N4 -> #DIV/0! | P4: =ROUND('1'!$I$26*Hoja1!D4,2) -> 3.41 | Q4: =+J4+P4 -> 6.51 | R4: =+'1'!#REF!+'1'!#REF! -> #REF! | S4: =+Q4/R4 -> #REF! | T4: 8 | U4: =ROUND(S4/T4,3) -> #REF! | V4: =ROUND(30/22,2) -> 1.36 | W4: =+U4*V4 -> #REF!
A5: 2 | B5: =+'2'!$B$1 -> Excavación a máquina con retroexcavadora | C5: =+'2'!$I$1 -> m3 | D5: 2.55 | E5: =+'2'!$G$35 -> 1.44 | F5: =+'2'!$G$36 -> 0.17 | G5: =+E5+F5 -> 1.61 | H5: =+D5*G5 -> 4.1055 | I5: =+'2'!$F$10 -> 0 | J5: =ROUND('2'!$I$10*Hoja1!D5,2) -> 0.1 | K5: =+'2'!F26 -> 0 | L5: =1/K5 -> #DIV/0! | M5: =+'2'!$D$26 -> 5 | N5: =+L5/M5 -> #DIV/0! | O5: =1/N5 -> #DIV/0! | P5: =ROUND('2'!$I$26*Hoja1!D5,2) -> 0.43 | Q5: =+J5+P5 -> 0.53 | R5: =+'2'!#REF!+'2'!#REF! -> #REF! | S5: =+Q5/R5 -> #REF! | T5: 8 | U5: =ROUND(S5/T5,3) -> #REF! | V5: =ROUND(30/22,2) -> 1.36 | W5: =+U5*V5 -> #REF!
A6: 3 | B6: =+'3'!$B$1 -> Relleno compactado con material de mejoramiento cribado | C6: =+'3'!$I$1 -> m3 | D6: 7.89 | E6: =+'3'!$G$35 -> 25.35 | F6: =+'3'!$G$36 -> 3.04 | G6: =+E6+F6 -> 28.39 | H6: =+D6*G6 -> 223.9971 | I6: =+'3'!$F$10 -> 0 | J6: =ROUND('3'!$I$10*Hoja1!D6,2) -> 9.47 | K6: =+'3'!$F$26 -> 0 | L6: =1/K6 -> #DIV/0! | M6: =+'3'!$D$26 -> 3 | N6: =+L6/M6 -> #DIV/0! | O6: =1/N6 -> #DIV/0! | P6: =ROUND('3'!$I$26*Hoja1!D6,2) -> 10.41 | Q6: =+J6+P6 -> 19.88 | R6: =+'3'!#REF!+'3'!#REF! -> #REF! | S6: =+Q6/R6 -> #REF! | T6: 8 | U6: =ROUND(S6/T6,3) -> #REF! | V6: =ROUND(30/22,2) -> 1.36 | W6: =+U6*V6 -> #REF!
A7: 4 | B7: Mampostería de bloque e=15cm | C7: m2 | D7: 101.75 | E7: =+'4(APU unificado)'!G35 -> 14.280574 | F7: =+'4(APU unificado)'!G36 -> 1.71 | G7: =+E7+F7 -> 15.990574 | H7: =+D7*G7 -> 1627.0409 | I7: =+'4(APU unificado)'!F9 -> 0 | J7: =ROUND('4(APU unificado)'!I9*Hoja1!D7,2) -> 64.71 | K7: =+'4(APU unificado)'!F26 -> 0 | L7: =1/K7 -> #DIV/0! | M7: =+'4(APU unificado)'!D26 -> 3 | N7: =+L7/M7 -> #DIV/0! | O7: =1/N7 -> #DIV/0! | P7: =ROUND('4(APU unificado)'!I26*Hoja1!D7,2) -> 140.42 | Q7: =+J7+P7 -> 205.13 | R7: =+'4(APU unificado)'!#REF!+'4(APU unificado)'!#REF! -> #REF! | S7: =+Q7/R7 -> #REF! | T7: 8 | U7: =ROUND(S7/T7,3) -> #REF! | V7: =ROUND(30/22,2) -> 1.36 | W7: =+U7*V7 -> #REF!
A8: 5 | B8: Transporte de materiales hasta 6 km, incluye pago en escombrera | C8: m3 | D8: 1003.64 | E8: =+'5'!G35 -> 0.9 | F8: =+'5'!G36 -> 0.11 | G8: =+E8+F8 -> 1.01 | H8: =+D8*G8 -> 1013.6764 | I8: =+'5'!$F$10 -> 0.02 | J8: =ROUND('5'!$I$10*Hoja1!D8,2) -> 20.07 | K8: =+'5'!$F$26 -> 0.02 | L8: =1/K8 -> 50 | M8: =+'5'!$D$26 -> 1 | N8: =+L8/M8 -> 50 | O8: =1/N8 -> 0.02 | P8: =ROUND('5'!$I$26*Hoja1!D8,2) -> 20.07 | Q8: =+J8+P8 -> 40.14 | R8: =+'5'!$L$10+'5'!$L$26 -> 2 | S8: =+Q8/R8 -> 20.07 | T8: 8 | U8: =ROUND(S8/T8,3) -> 2.509 | V8: =ROUND(30/22,2) -> 1.36 | W8: =+U8*V8 -> 3.41224
A10: Nota:
A12: Columna JORNADA LABORAL se elimina y se le coloca en un sitio específico en el formulario de GIPROY
A13: Columna FACTOR DE CONVERSION se elimina y se le coloca en un sitio específico en el formulario de GIPROY
A14: Si los APUS sólo tienen material o transporte, con lo cual no existiría un tiempo y por lo tanto carecería de un cálculo de duración para exportación a project, el resultado de los días y todo lo que ello conlleva debe tener valor CERO y con este valor de tiempo, exportar a project, verificando que los recursos respectivos si se carguen allá.

Sheet 1
A1: DESCRIPCIÓN: | B1: Excavación manual, zanja 0-2 m, material sin clasificar | H1: UNIDAD: | I1: m3
A3: RENDIMIENTO: | B3: horas/unidad
A5: CODIGO | B5: DESCRIPCIÓN | C5: UNIDAD | D5: CANTIDAD | E5: PRECIO | F5: RENDIMIENTO | G5: TOTAL | H5: % COSTO | I5: TRABAJO
A6: EQUIPOS / HERRAMIENTAS
B7: Herramientas varias | C7: hora | D7: 1 | E7: 0.5 | F7: 2 | G7: =ROUND(D7*E7*F7,2) -> 1 | H7: =+G7/$G$35 -> 0.11185682 | I7: =+D7*F7 -> 2
B10: SUBTOTAL 1 | G10: =SUM(G7:G9) -> 1 | H10: =+G10/$G$35 -> 0.11185682 | I10: =SUM(I7:I9) -> 2
A11: MATERIALES
B15: SUBTOTAL 2 | G15: =SUM(G12:G14) -> 0 | H15: =+G15/$G$35 -> 0
A16: TRANSPORTE
B20: SUBTOTAL 3 | G20: =SUM(G17:G19) -> 0 | H20: =+G20/$G$35 -> 0
A21: MANO DE OBRA
B22: Peón | C22: hora | D22: 1 | E22: 3.46 | F22: 2 | G22: =ROUND(D22*E22*F22,2) -> 6.92 | H22: =+G22/$G$35 -> 0.77404922 | I22: =+D22*F22 -> 2
B23: Maestro de obra | C23: hora | D23: 1 | E23: 5.11 | F23: 0.2 | G23: =ROUND(D23*E23*F23,2) -> 1.02 | H23: =+G23/$G$35 -> 0.11409396 | I23: =+D23*F23 -> 0.2
B26: SUBTOTAL 4 | D26: =SUM(D22:D25) -> 2 | G26: =SUM(G22:G25) -> 7.94 | H26: =+G26/$G$35 -> 0.88814318 | I26: =SUM(I22:I25) -> 2.2
A27: SEGURIDAD INDUSTRIAL
B32: SUBTOTAL 5 | G32: =SUM(G28:G31) -> 0 | H32: =+G32/$G$35 -> 0
E34: DURACIÓN ACTIVIDAD | F34: 2 | G34: Se escoge el mayor rendimiento de entre los rendimientos de mano de obra y equipos y herramientas. Se prioriza el rendimiento de mano de obra siempre como canidato
E35: COSTO DIRECTO | G35: =+G10+G15+G20+G26+G32 -> 8.94
E36: INDIRECTO (12%) | G36: =+ROUND(0.12*G35,2) -> 1.07
E37: COSTO TOTAL | G37: =+G35+G36 -> 10.01

Sheet 2
A1: DESCRIPCIÓN: | B1: Excavación a máquina con retroexcavadora | H1: UNIDAD: | I1: m3
A3: RENDIMIENTO: | B3: horas/unidad
A5: CODIGO | B5: DESCRIPCIÓN | C5: UNIDAD | D5: CANTIDAD | E5: PRECIO | F5: RENDIMIENTO | G5: TOTAL | H5: % COSTO | I5: TRABAJO
A6: EQUIPOS / HERRAMIENTAS
B7: Retroexcavadora | C7: hora | D7: 1 | E7: 20 | F7: 0.0385 | G7: =ROUND(D7*E7*F7,2) -> 0.77 | H7: =+G7/$G$35 -> 0.53472222 | I7: =+D7*F7 -> 0.0385
B10: SUBTOTAL 1 | G10: =SUM(G7:G9) -> 0.77 | H10: =+G10/$G$35 -> 0.53472222 | I10: =SUM(I7:I9) -> 0.0385
A11: MATERIALES
B15: SUBTOTAL 2 | G15: =SUM(G12:G14) -> 0 | H15: =+G15/$G$35 -> 0
A16: TRANSPORTE
B20: SUBTOTAL 3 | G20: =SUM(G17:G19) -> 0 | H20: =+G20/$G$35 -> 0
A21: MANO DE OBRA
B22: Peón | C22: hora | D22: 2 | E22: 3.46 | F22: 0.0385 | G22: =ROUND(D22*E22*F22,2) -> 0.27 | H22: =+G22/$G$35 -> 0.1875 | I22: =+D22*F22 -> 0.077
B23: Albañil | C23: hora | D23: 1 | E23: 4.29 | F23: 0.0385 | G23: =ROUND(D23*E23*F23,2) -> 0.17 | H23: =+G23/$G$35 -> 0.11805556 | I23: =+D23*F23 -> 0.0385
B24: Operador | C24: hora | D24: 1 | E24: 3.82 | F24: 0.0385 | G24: =ROUND(D24*E24*F24,2) -> 0.15 | H24: =+G24/$G$35 -> 0.10416667 | I24: =+D24*F24 -> 0.0385
B25: Maestro de obra | C25: hora | D25: 1 | E25: 5.11 | F25: 0.0154 | G25: =ROUND(D25*E25*F25,2) -> 0.08 | H25: =+G25/$G$35 -> 0.055555556 | I25: =+D25*F25 -> 0.0154
B26: SUBTOTAL 4 | D26: =SUM(D22:D25) -> 5 | G26: =SUM(G22:G25) -> 0.67 | H26: =+G26/$G$35 -> 0.46527778 | I26: =SUM(I22:I25) -> 0.1694
A27: SEGURIDAD INDUSTRIAL
B32: SUBTOTAL 5 | G32: =SUM(G28:G31) -> 0 | H32: =+G32/$G$35 -> 0
E34: DURACIÓN ACTIVIDAD | F34: 0.0385 | G34: Se escoge el mayor rendimiento de entre los rendimientos de mano de obra y equipos y herramientas. Se prioriza el rendimiento de mano de obra siempre como canidato
E35: COSTO DIRECTO | G35: =+G10+G15+G20+G26+G32 -> 1.44
E36: INDIRECTO (12%) | G36: =+ROUND(0.12*G35,2) -> 0.17
E37: COSTO TOTAL | G37: =+G35+G36 -> 1.61

Sheet 3
A1: DESCRIPCIÓN: | B1: Relleno compactado con material de mejoramiento cribado | H1: UNIDAD: | I1: m3
A3: RENDIMIENTO: | B3: horas/unidad
A5: CODIGO | B5: DESCRIPCIÓN | C5: UNIDAD | D5: CANTIDAD | E5: PRECIO | F5: RENDIMIENTO | G5: TOTAL | H5: % COSTO | I5: TRABAJO
A6: EQUIPOS / HERRAMIENTAS
B7: Herramientas varias | C7: hora | D7: 1 | E7: 0.5 | F7: 0.6 | G7: =ROUND(D7*E7*F7,2) -> 0.3 | H7: =+G7/$G$35 -> 0.01183432 | I7: =+D7*F7 -> 0.6
B8: Plancha vibratoria | C8: hora | D8: 1 | E8: 3.5 | F8: 0.6 | G8: =ROUND(D8*E8*F8,2) -> 2.1 | H8: =+G8/$G$35 -> 0.082840237 | I8: =+D8*F8 -> 0.6
B10: SUBTOTAL 1 | G10: =SUM(G7:G9) -> 2.4 | H10: =+G10/$G$35 -> 0.094674556 | I10: =SUM(I7:I9) -> 1.2
A11: MATERIALES
B12: Mejoramiento cribado | C12: m3 | D12: 1.31 | E12: 13.5 | G12: =ROUND(D12*E12,2) -> 17.69 | H12: =+G12/$G$35 -> 0.69783037
B15: SUBTOTAL 2 | G15: =SUM(G12:G14) -> 17.69 | H15: =+G15/$G$35 -> 0.69783037
A16: TRANSPORTE
B20: SUBTOTAL 3 | G20: =SUM(G17:G19) -> 0 | H20: =+G20/$G$35 -> 0
A21: MANO DE OBRA
B22: Peón | C22: hora | D22: 1 | E22: 3.46 | F22: 0.6 | G22: =ROUND(D22*E22*F22,2) -> 2.08 | H22: =+G22/$G$35 -> 0.082051282 | I22: =+D22*F22 -> 0.6
B23: Albañil | C23: hora | D23: 1 | E23: 4.29 | F23: 0.6 | G23: =ROUND(D23*E23*F23,2) -> 2.57 | H23: =+G23/$G$35 -> 0.10138067 | I23: =+D23*F23 -> 0.6
B24: Maestro de obra | C24: hora | D24: 1 | E24: 5.11 | F24: 0.12 | G24: =ROUND(D24*E24*F24,2) -> 0.61 | H24: =+G24/$G$35 -> 0.024063116 | I24: =+D24*F24 -> 0.12
B26: SUBTOTAL 4 | D26: =SUM(D22:D24) -> 3 | G26: =SUM(G22:G24) -> 5.26 | H26: =+G26/$G$35 -> 0.20749507 | I26: =SUM(I22:I24) -> 1.32
A27: SEGURIDAD INDUSTRIAL
B32: SUBTOTAL 5 | G32: =SUM(G28:G31) -> 0 | H32: =+G32/$G$35 -> 0
E34: DURACIÓN ACTIVIDAD | F34: 0.6 | G34: Se escoge el mayor rendimiento de entre los rendimientos de mano de obra y equipos y herramientas. Se prioriza el rendimiento de mano de obra siempre como canidato
E35: COSTO DIRECTO | G35: =+G10+G15+G20+G26+G32 -> 25.35
E36: INDIRECTO (12%) | G36: =+ROUND(0.12*G35,2) -> 3.04
E37: COSTO TOTAL | G37: =+G35+G36 -> 28.39

Sheet 4(APU)
A1: DESCRIPCIÓN: | B1: Mampostería de bloque e=15cm | H1: UNIDAD: | I1: m2
A3: RENDIMIENTO: | B3: horas/unidad
A5: CODIGO | B5: DESCRIPCIÓN | C5: UNIDAD | D5: CANTIDAD | E5: PRECIO | F5: RENDIMIENTO | G5: TOTAL | H5: % COSTO | I5: TRABAJO
A6: EQUIPOS / HERRAMIENTAS
B7: Herramientas varias | C7: hora | D7: 1 | E7: 0.5 | F7: 0.6 | G7: =ROUND(D7*E7*F7,2) -> 0.3 | H7: =+G7/$G$34 -> 0.021008403 | I7: =+D7*F7 -> 0.6
B9: SUBTOTAL 1 | G9: =SUM(G7:G8) -> 0.3 | H9: =+G9/$G$34 -> 0.021008403 | I9: =SUM(I7:I8) -> 0.6
A10: MATERIALES
B11: Bloque de 40 × 20 × 15 cm | C11: u | D11: 13 | E11: 0.5 | G11: =ROUND(D11*E11,2) -> 6.5 | H11: =+G11/$G$34 -> 0.45518207
B12: Mortero de cemento 1:3 | C12: m3 | D12: 0.02 | E12: 110.95 | G12: =ROUND(D12*E12,2) -> 2.22 | H12: =+G12/$G$34 -> 0.15546218
B14: SUBTOTAL 2 | G14: =SUM(G11:G13) -> 8.72 | H14: =+G14/$G$34 -> 0.61064426
A15: TRANSPORTE
B19: SUBTOTAL 3 | G19: =SUM(G16:G18) -> 0 | H19: =+G19/$G$34 -> 0
A20: MANO DE OBRA
B21: Peón | C21: hora | D21: 1 | E21: 3.46 | F21: 0.6 | G21: =ROUND(D21*E21*F21,2) -> 2.08 | H21: =+G21/$G$34 -> 0.14565826 | I21: =+D21*F21 -> 0.6
B22: Albañil | C22: hora | D22: 1 | E22: 4.29 | F22: 0.6 | G22: =ROUND(D22*E22*F22,2) -> 2.57 | H22: =+G22/$G$34 -> 0.17997199 | I22: =+D22*F22 -> 0.6
B23: Maestro de obra | C23: hora | D23: 1 | E23: 5.11 | F23: 0.12 | G23: =ROUND(D23*E23*F23,2) -> 0.61 | H23: =+G23/$G$34 -> 0.042717087 | I23: =+D23*F23 -> 0.12
B25: SUBTOTAL 4 | D25: =SUM(D21:D23) -> 3 | G25: =SUM(G21:G23) -> 5.26 | H25: =+G25/$G$34 -> 0.36834734 | I25: =SUM(I21:I23) -> 1.32
A26: SEGURIDAD INDUSTRIAL
B31: SUBTOTAL 5 | G31: =SUM(G27:G30) -> 0 | H31: =+G31/$G$34 -> 0
E33: DURACIÓN ACTIVIDAD | F33: 0.6 | G33: Se escoge el mayor rendimiento de entre los rendimientos de mano de obra y equipos y herramientas. Se prioriza el rendimiento de mano de obra siempre como canidato
E34: COSTO DIRECTO | G34: =+G9+G14+G19+G25+G31 -> 14.28
E35: INDIRECTO (12%) | G35: =+ROUND(0.12*G34,2) -> 1.71
E36: COSTO TOTAL | G36: =+G34+G35 -> 15.99

Sheet 4(APU anidado)
A1: DESCRIPCIÓN: | B1: Mortero de cemento 1:3 | H1: UNIDAD: | I1: m3
A3: RENDIMIENTO: | B3: horas/unidad
A5: CODIGO | B5: DESCRIPCIÓN | C5: UNIDAD | D5: CANTIDAD | E5: PRECIO | F5: RENDIMIENTO | G5: TOTAL | H5: % COSTO | I5: TRABAJO
A6: EQUIPOS / HERRAMIENTAS
B7: Herramientas varias | C7: hora | D7: 2 | E7: 0.5 | F7: 0.9 | G7: =ROUND(D7*E7*F7,2) -> 0.9 | H7: =+G7/$G$34 -> 0.0081117621 | I7: =+D7*F7 -> 1.8
B9: SUBTOTAL 1 | G9: =SUM(G7:G8) -> 0.9 | H9: =+G9/$G$34 -> 0.0081117621 | I9: =SUM(I7:I8) -> 1.8
A10: MATERIALES
B11: Cemento | C11: saco | D11: 10 | E11: 7.25 | G11: =ROUND(D11*E11,2) -> 72.5 | H11: =+G11/$G$34 -> 0.6534475
B12: Arena | C12: m3 | D12: 1.15 | E12: 20.5 | G12: =ROUND(D12*E12,2) -> 23.58 | H12: =+G12/$G$34 -> 0.21252817
B13: Agua | C13: l | D13: 250 | E13: 0.01 | G13: =ROUND(D13*E13,2) -> 2.5 | H13: =+G13/$G$34 -> 0.022532672
B14: SUBTOTAL 2 | G14: =SUM(G11:G13) -> 98.58 | H14: =+G14/$G$34 -> 0.88850834
A15: TRANSPORTE
B19: SUBTOTAL 3 | G19: =SUM(G16:G18) -> 0 | H19: =+G19/$G$34 -> 0
A20: MANO DE OBRA
B21: Peón | C21: hora | D21: 2 | E21: 3.46 | F21: 0.9 | G21: =ROUND(D21*E21*F21,2) -> 6.23 | H21: =+G21/$G$34 -> 0.05615142 | I21: =+D21*F21 -> 1.8
B22: Albañil | C22: hora | D22: 1 | E22: 4.29 | F22: 0.9 | G22: =ROUND(D22*E22*F22,2) -> 3.86 | H22: =+G22/$G$34 -> 0.034790446 | I22: =+D22*F22 -> 0.9
B23: Maestro de obra | C23: hora | D23: 1 | E23: 5.11 | F23: 0.27 | G23: =ROUND(D23*E23*F23,2) -> 1.38 | H23: =+G23/$G$34 -> 0.012438035 | I23: =+D23*F23 -> 0.27
B25: SUBTOTAL 4 | D25: =SUM(D21:D23) -> 4 | G25: =SUM(G21:G23) -> 11.47 | H25: =+G25/$G$34 -> 0.1033799 | I25: =SUM(I21:I23) -> 2.97
A26: SEGURIDAD INDUSTRIAL
B31: SUBTOTAL 5 | G31: =SUM(G27:G30) -> 0 | H31: =+G31/$G$34 -> 0
E33: DURACIÓN ACTIVIDAD | F33: 0.9 | G33: Se escoge el mayor rendimiento de entre los rendimientos de mano de obra y equipos y herramientas. Se prioriza el rendimiento de mano de obra siempre como canidato
E34: COSTO DIRECTO | G34: =+G9+G14+G19+G25+G31 -> 110.95
E35: INDIRECTO (12%) | G35: =+ROUND(0.12*G34,2) -> 13.31
E36: COSTO TOTAL | G36: =+G34+G35 -> 124.26

Sheet 4(APU anidado con cantidad)
A1: DESCRIPCIÓN: | B1: Mortero de cemento 1:3 | H1: UNIDAD: | I1: m3
A3: RENDIMIENTO: | B3: horas/unidad
A5: CODIGO | B5: DESCRIPCIÓN | C5: UNIDAD | D5: CANTIDAD | E5: PRECIO | F5: RENDIMIENTO | G5: TOTAL | H5: % COSTO | I5: TRABAJO
A6: EQUIPOS / HERRAMIENTAS
B7: Herramientas varias | C7: hora | D7: =+'4(APU anidado)'!D7 -> 2 | E7: 0.5 | F7: =+'4(APU anidado)'!F7*'4(APU)'!$D$12 -> 0.018 | G7: =ROUND(D7*E7*F7,2) -> 0.02 | H7: =+G7/$G$34 -> 0.009009009 | I7: =+D7*F7 -> 0.036
B9: SUBTOTAL 1 | G9: =SUM(G7:G8) -> 0.02 | H9: =+G9/$G$34 -> 0.009009009 | I9: =SUM(I7:I8) -> 0.036
A10: MATERIALES
B11: Cemento | C11: saco | D11: ='4(APU)'!$D$12*'4(APU anidado)'!D11 -> 0.2 | E11: 7.25 | G11: =ROUND(D11*E11,2) -> 1.45 | H11: =+G11/$G$34 -> 0.65315315
B12: Arena | C12: m3 | D12: ='4(APU)'!$D$12*'4(APU anidado)'!D12 -> 0.023 | E12: 20.5 | G12: =ROUND(D12*E12,2) -> 0.47 | H12: =+G12/$G$34 -> 0.21171171
B13: Agua | C13: l | D13: ='4(APU)'!$D$12*'4(APU anidado)'!D13 -> 5 | E13: 0.01 | G13: =ROUND(D13*E13,2) -> 0.05 | H13: =+G13/$G$34 -> 0.022522523
B14: SUBTOTAL 2 | G14: =SUM(G11:G13) -> 1.97 | H14: =+G14/$G$34 -> 0.88738739
A15: TRANSPORTE
B19: SUBTOTAL 3 | G19: =SUM(G16:G18) -> 0 | H19: =+G19/$G$34 -> 0
A20: MANO DE OBRA
B21: Peón | C21: hora | D21: =+'4(APU anidado)'!D21 -> 2 | E21: 3.46 | F21: =+'4(APU anidado)'!F21*'4(APU)'!$D$12 -> 0.018 | G21: =ROUND(D21*E21*F21,2) -> 0.12 | H21: =+G21/$G$34 -> 0.054054054 | I21: =+D21*F21 -> 0.036
B22: Albañil | C22: hora | D22: =+'4(APU anidado)'!D22 -> 1 | E22: 4.29 | F22: =+'4(APU anidado)'!F22*'4(APU)'!$D$12 -> 0.018 | G22: =ROUND(D22*E22*F22,2) -> 0.08 | H22: =+G22/$G$34 -> 0.036036036 | I22: =+D22*F22 -> 0.018
B23: Maestro de obra | C23: hora | D23: =+'4(APU anidado)'!D23 -> 1 | E23: 5.11 | F23: =+'4(APU anidado)'!F23*'4(APU)'!$D$12 -> 0.0054 | G23: =ROUND(D23*E23*F23,2) -> 0.03 | H23: =+G23/$G$34 -> 0.013513514 | I23: =+D23*F23 -> 0.0054
B25: SUBTOTAL 4 | D25: =SUM(D21:D23) -> 4 | G25: =SUM(G21:G23) -> 0.23 | H25: =+G25/$G$34 -> 0.1036036 | I25: =SUM(I21:I23) -> 0.0594
A26: SEGURIDAD INDUSTRIAL
B31: SUBTOTAL 5 | G31: =SUM(G27:G30) -> 0 | H31: =+G31/$G$34 -> 0
E33: DURACIÓN ACTIVIDAD | F33: 0.018 | G33: Se escoge el mayor rendimiento de entre los rendimientos de mano de obra y equipos y herramientas. Se prioriza el rendimiento de mano de obra siempre como canidato
E34: COSTO DIRECTO | G34: =+G9+G14+G19+G25+G31 -> 2.22 | H34: Debe verificarse que este valor sea igual al que está en el precio unitario principal
E35: INDIRECTO (12%) | G35: =+ROUND(0.12*G34,2) -> 0.27
E36: COSTO TOTAL | G36: =+G34+G35 -> 2.49

Sheet 4(APU unificado)
A1: DESCRIPCIÓN: | B1: Mampostería de bloque e=15cm | H1: UNIDAD: | I1: m2
A3: RENDIMIENTO: | B3: horas/unidad
A5: CODIGO | B5: DESCRIPCIÓN | C5: UNIDAD | D5: CANTIDAD | E5: PRECIO | F5: RENDIMIENTO | G5: TOTAL | H5: % COSTO | I5: TRABAJO
A6: EQUIPOS / HERRAMIENTAS
B7: Herramientas varias | C7: hora | D7: 1 | E7: 0.5 | F7: =+M7 -> 0.636 | G7: =+D7*E7*F7 -> 0.318 | H7: =+G7/$G$35 -> 0.022268012 | I7: =+D7*F7 -> 0.636 | L7: =+'4(APU)'!I7+'4(APU anidado con cantidad)'!I7 -> 0.636 | M7: =+L7/D7 -> 0.636 | Z7: =('4(APU anidado)'!D7*'4(APU)'!$D$12)+'4(APU)'!D7 -> 1.04 | AA7: =+E7 -> 0.5 | AB7: 0.6 | AC7: =+Z7*AA7*AB7 -> 0.312
B9: SUBTOTAL 1 | G9: =SUM(G7:G8) -> 0.318 | H9: =+G9/$G$35 -> 0.022268012 | I9: =SUM(I7:I8) -> 0.636
A10: MATERIALES
B11: Bloque de 40 × 20 × 15 cm | C11: u | D11: =+'4(APU)'!D11 -> 13 | E11: 0.5 | G11: =ROUND(D11*E11,2) -> 6.5 | H11: =+G11/$G$35 -> 0.45516378 | AC11: =+G11 -> 6.5
B12: Cemento | C12: saco | D12: =10*'4(APU)'!D12 -> 0.2 | E12: 7.25 | G12: =ROUND(D12*E12,2) -> 1.45 | H12: =+G12/$G$35 -> 0.10153653 | AC12: =+G12 -> 1.45
B13: Arena | C13: m3 | D13: =1.15*'4(APU)'!$D$12 -> 0.023 | E13: 20.5 | G13: =ROUND(D13*E13,2) -> 0.47 | H13: =+G13/$G$35 -> 0.032911842 | AC13: =+G13 -> 0.47
B14: Agua | C14: l | D14: =250*'4(APU)'!$D$12 -> 5 | E14: 0.01 | G14: =ROUND(D14*E14,2) -> 0.05 | H14: =+G14/$G$35 -> 0.0035012598 | AC14: =+G14 -> 0.05
B15: SUBTOTAL 2 | G15: =SUM(G11:G14) -> 8.47 | H15: =+G15/$G$35 -> 0.59311341
A16: TRANSPORTE
B20: SUBTOTAL 3 | G20: =SUM(G17:G19) -> 0 | H20: =+G20/$G$35 -> 0
A21: MANO DE OBRA
B22: Peón | C22: hora | D22: 1 | E22: 3.46 | F22: =+M22 -> 0.636 | G22: =+D22*E22*F22 -> 2.20056 | H22: =+G22/$G$35 -> 0.15409465 | I22: =+D22*F22 -> 0.636 | L22: =+'4(APU)'!I21+'4(APU anidado con cantidad)'!I21 -> 0.636 | M22: =+L22/D22 -> 0.636 | Z22: =('4(APU anidado)'!D21*'4(APU)'!$D$12)+'4(APU)'!D21 -> 1.04 | AA22: =+E22 -> 3.46 | AB22: 0.6 | AC22: =+Z22*AA22*AB22 -> 2.15904
B23: Albañil | C23: hora | D23: 1 | E23: 4.29 | F23: =+M23 -> 0.618 | G23: =+D23*E23*F23 -> 2.65122 | H23: =+G23/$G$35 -> 0.1856522 | I23: =+D23*F23 -> 0.618 | L23: =+'4(APU)'!I22+'4(APU anidado con cantidad)'!I22 -> 0.618 | M23: =+L23/D23 -> 0.618 | Z23: =('4(APU anidado)'!D22*'4(APU)'!$D$12)+'4(APU)'!D22 -> 1.02 | AA23: =+E23 -> 4.29 | AB23: 0.6 | AC23: =+Z23*AA23*AB23 -> 2.62548
B24: Maestro de obra | C24: hora | D24: 1 | E24: 5.11 | F24: =+M24 -> 0.1254 | G24: =+D24*E24*F24 -> 0.640794 | H24: =+G24/$G$35 -> 0.044871726 | I24: =+D24*F24 -> 0.1254 | L24: =+'4(APU)'!I23+'4(APU anidado con cantidad)'!I23 -> 0.1254 | M24: =+L24/D24 -> 0.1254 | Z24: =('4(APU anidado)'!D23*'4(APU)'!$D$12)+'4(APU)'!D23 -> 1.02 | AA24: =+E24 -> 5.11 | AB24: 0.12 | AC24: =+Z24*AA24*AB24 -> 0.625464
B26: SUBTOTAL 4 | D26: =SUM(D22:D24) -> 3 | G26: =SUM(G22:G24) -> 5.492574 | H26: =+G26/$G$35 -> 0.38461857 | I26: =ROUND(SUM(I22:I24),2) -> 1.38
A27: SEGURIDAD INDUSTRIAL
B32: SUBTOTAL 5 | G32: =SUM(G28:G31) -> 0 | H32: =+G32/$G$35 -> 0
E34: DURACIÓN ACTIVIDAD | F34: 0.3089 | G34: Se escoge el mayor rendimiento de entre los rendimientos de mano de obra y equipos y herramientas. Se prioriza el rendimiento de mano de obra siempre como canidato
E35: COSTO DIRECTO | G35: =+G9+G15+G20+G26+G32 -> 14.280574 | H35: Debe verificarse que este valor sea igual al que está en el precio unitario principal
E36: INDIRECTO (12%) | G36: =+ROUND(0.12*G35,2) -> 1.71
E37: COSTO TOTAL | G37: =+G35+G36 -> 15.990574

Sheet 5
A1: DESCRIPCIÓN: | B1: Transporte de materiales hasta 6 km, incluye pago en escombrera | H1: UNIDAD: | I1: m3
A3: RENDIMIENTO: | B3: horas/unidad
A5: CODIGO | B5: DESCRIPCIÓN | C5: UNIDAD | D5: CANTIDAD | E5: PRECIO | F5: RENDIMIENTO | G5: TOTAL | H5: % COSTO | I5: TRABAJO | J5: % TIEMPO | K5: Unidades de Recurso Calculado | L5: Unidades de Recurso Asumido
A6: EQUIPOS / HERRAMIENTAS
B7: Volqueta 8m3 | C7: hora | D7: 1 | E7: 20 | F7: 0.02 | G7: =ROUND(D7*E7*F7,2) -> 0.4 | H7: =+G7/$G$35 -> 0.44444444 | I7: =+D7*F7 -> 0.02 | J7: =ROUND(F7/$F$34,4) -> 1 | K7: =+D7*J7 -> 1 | L7: =+ROUND(K7,2) -> 1
B10: SUBTOTAL 1 | F10: =SUM(F7:F9) -> 0.02 | G10: =SUM(G7:G9) -> 0.4 | H10: =+G10/$G$35 -> 0.44444444 | I10: =SUM(I7:I9) -> 0.02 | L10: =SUM(L7:L9) -> 1
A11: MATERIALES
B12: Pago por concepto de disposición de materiales en escombrera | C12: m3 | D12: 1 | E12: 0.4 | G12: =ROUND(D12*E12,2) -> 0.4 | H12: =+G12/$G$35 -> 0.44444444 | L12: la cantidad del presupuesto multiplicado por la cantidad de cada material
B15: SUBTOTAL 2 | G15: =SUM(G12:G14) -> 0.4 | H15: =+G15/$G$35 -> 0.44444444
A16: TRANSPORTE
B20: SUBTOTAL 3 | G20: =SUM(G17:G19) -> 0 | H20: =+G20/$G$35 -> 0
A21: MANO DE OBRA
B22: Chofer de volqueta | C22: hora | D22: 1 | E22: 5 | F22: 0.02 | G22: =ROUND(D22*E22*F22,2) -> 0.1 | H22: =+G22/$G$35 -> 0.11111111 | I22: =+D22*F22 -> 0.02 | J22: =ROUND(F22/$F$34,4) -> 1 | K22: =+D22*J22 -> 1 | L22: =+ROUND(K22,2) -> 1
B26: SUBTOTAL 4 | D26: =SUM(D22:D24) -> 1 | F26: =SUM(F22:F24) -> 0.02 | G26: =SUM(G22:G24) -> 0.1 | H26: =+G26/$G$35 -> 0.11111111 | I26: =SUM(I22:I24) -> 0.02 | L26: =SUM(L22:L24) -> 1
A27: SEGURIDAD INDUSTRIAL
B32: SUBTOTAL 5 | G32: =SUM(G28:G31) -> 0 | H32: =+G32/$G$35 -> 0
E34: DURACIÓN ACTIVIDAD | F34: =+IF(F26>F10,F26,F10) -> 0.02 | G34: Se escoge el mayor rendimiento entre los totales del rendimiento de mano de obra y equipos y herramientas
E35: COSTO DIRECTO | G35: =+G10+G15+G20+G26+G32 -> 0.9
E36: INDIRECTO (12%) | G36: =+ROUND(0.12*G35,2) -> 0.11
E37: COSTO TOTAL | G37: =+G35+G36 -> 1.01
