Workbook

Sheet Calculo
A1: TABLA DE CÁLCULO DE DÍAS LABORABLES Y DÍAS CALENDARIO
A2: N° | B2: Item | C2: Descripción | D2: Unidad | E2: Cantidad | F2: P.Unitario | I2: P.Total | J2: Rendimiento Unitario Total Equipo / Herramienta (h/u) | K2: Trabajo Equipo / Herramientas (h-EH) | L2: Rendimiento Unitario Total Mano de Obra (h/u) | M2: Trabajo (h-H) | N2: TRABAJO TOTAL | O2: UNIDADES DE RECURSOS ASUMIDOS TOTALES | P2: Duración (horas) | Q2: Numero de Hombres en Cuadrilla | R2: Jornada Laboral (horas) | S2: Dias útiles | T2: Factor de Conversión (Días Mes / Días Laborables Mensual) | U2: Dias Calendario
F3: Costo Directo | G3: Costo Indirecto | H3: P. Unitario
B4: 1 | C4: =+'1'!$B$1 -> Excavación manual, zanja 0-2 m, material sin clasificar | D4: =+'1'!$I$1 -> m3 | E4: 1.55 | F4: =+'1'!$G$35 -> 8.94 | G4: =+'1'!$G$36 -> 1.07 | H4: =+F4+G4 -> 10.01 | I4: =+E4*H4 -> 15.5155 | J4: =+'1'!$F$10 -> 2 | K4: =ROUND('1'!$I$10*Calculo!E4,2) -> 3.1 | L4: =+'1'!F26 -> 2.2 | M4: =ROUND('1'!$I$26*Calculo!E4,2) -> 3.41 | N4: =+K4+M4 -> 6.51 | O4: =+'1'!L10+'1'!L26 -> 1.91 | P4: =+N4/O4 -> 3.408377 | Q4: =+'1'!$D$26 -> 2 | R4: 8 | S4: =ROUND(P4/R4,3) -> 0.426 | T4: =ROUND(30/22,2) -> 1.36 | U4: =+S4*T4 -> 0.57936
B5: 2 | C5: =+'2'!$B$1 -> Excavación a máquina con retroexcavadora | D5: =+'2'!$I$1 -> m3 | E5: 2.55 | F5: =+'2'!$G$35 -> 1.44 | G5: =+'2'!$G$36 -> 0.17 | H5: =+F5+G5 -> 1.61 | I5: =+E5*H5 -> 4.1055 | J5: =+'2'!$F$10 -> 0.0385 | K5: =ROUND('2'!$I$10*Calculo!E5,2) -> 0.1 | L5: =+'2'!F26 -> 0.1309 | M5: =ROUND('2'!$I$26*Calculo!E5,2) -> 0.43 | N5: =+K5+M5 -> 0.53 | O5: =+'2'!L10+'2'!L26 -> 1.58 | P5: =+N5/O5 -> 0.33544304 | Q5: =+'2'!$D$26 -> 5 | R5: 8 | S5: =ROUND(P5/R5,3) -> 0.042 | T5: =ROUND(30/22,2) -> 1.36 | U5: =+S5*T5 -> 0.05712
B6: 3 | C6: =+'3'!$B$1 -> Relleno compactado con material de mejoramiento cribado | D6: =+'3'!$I$1 -> m3 | E6: 7.89 | F6: =+'3'!$G$35 -> 25.35 | G6: =+'3'!$G$36 -> 3.04 | H6: =+F6+G6 -> 28.39 | I6: =+E6*H6 -> 223.9971 | J6: =+'3'!$F$10 -> 1.2 | K6: =ROUND('3'!$I$10*Calculo!E6,2) -> 9.47 | L6: =+'3'!$F$26 -> 1.32 | M6: =ROUND('3'!$I$26*Calculo!E6,2) -> 10.41 | N6: =+K6+M6 -> 19.88 | O6: =+'3'!$L$10+'3'!$L$26 -> 1.89 | P6: =+N6/O6 -> 10.518519 | Q6: =+'3'!$D$26 -> 3 | R6: 8 | S6: =ROUND(P6/R6,3) -> 1.315 | T6: =ROUND(30/22,2) -> 1.36 | U6: =+S6*T6 -> 1.7884
B7: 4 | C7: Mampostería de bloque e=15cm | D7: m2 | E7: 101.75 | F7: =+'4(APU unificado)'!G35 -> 14.28 | G7: =+'4(APU unificado)'!G36 -> 1.71 | H7: 1 | I7: =+E7*H7 -> 101.75 | J7: =+'4(APU unificado)'!F9 -> 0.21333333 | K7: =ROUND('4(APU unificado)'!I9*Calculo!E7,2) -> 65.12 | L7: =+'4(APU unificado)'!F26 -> 0.58342617 | M7: =ROUND('4(APU unificado)'!I26*Calculo!E7,2) -> 140.42 | N7: =+K7+M7 -> 205.54 | O7: =+'4(APU unificado)'!L9+'4(APU unificado)'!L26 -> 3.46 | P7: =+N7/O7 -> 59.404624 | Q7: =+'4(APU unificado)'!D26 -> 7 | R7: 8 | S7: =ROUND(P7/R7,3) -> 7.426 | T7: =ROUND(30/22,2) -> 1.36 | U7: =+S7*T7 -> 10.09936
B8: 5 | C8: Transporte de materiales hasta 6 km, incluye pago en escombrera | D8: m3 | E8: 1003.64 | F8: =+'5'!G35 -> 0.9 | G8: =+'5'!G36 -> 0.11 | H8: =+F8+G8 -> 1.01 | I8: =+E8*H8 -> 1013.6764 | J8: =+'5'!$F$10 -> 0.02 | K8: =ROUND('5'!$I$10*Calculo!E8,2) -> 20.07 | L8: =+'5'!$F$26 -> 0.02 | M8: =ROUND('5'!$I$26*Calculo!E8,2) -> 20.07 | N8: =+K8+M8 -> 40.14 | O8: =+'5'!$L$10+'5'!$L$26 -> 2 | P8: =+N8/O8 -> 20.07 | Q8: =+'5'!$D$26 -> 1 | R8: 8 | S8: =ROUND(P8/R8,3) -> 2.509 | T8: =ROUND(30/22,2) -> 1.36 | U8: =+S8*T8 -> 3.41224
B9: 6 | C9: Cargado, transporte y descarga de encofrados | D9: Viaje 200 qq | E9: 41.21 | F9: =+'6'!G35 -> 75.58 | G9: =+'6'!G36 -> 9.07 | H9: =+F9+G9 -> 84.65 | I9: =+E9*H9 -> 3488.4265 | J9: =+'6'!$F$10 -> 4.4 | K9: =ROUND('6'!$I$10*Calculo!E9,2) -> 181.32 | L9: =+'6'!$F$26 -> 2.525 | M9: =ROUND('6'!$I$26*Calculo!E9,2) -> 516.16 | N9: =+K9+M9 -> 697.48 | O9: =+'6'!$L$10+'6'!$L$26 -> 3.85 | P9: =+N9/O9 -> 181.16364 | Q9: =+'6'!$D$26 -> 6 | R9: 8 | S9: =ROUND(P9/R9,3) -> 22.645 | T9: =ROUND(30/22,2) -> 1.36 | U9: =+S9*T9 -> 30.7972

Sheet 6
A1: DESCRIPCIÓN: | B1: Cargado, transporte y descarga de encofrados | H1: UNIDAD: | I1: m3
A3: RENDIMIENTO: | B3: Viaje 200 qq
A5: CODIGO | B5: DESCRIPCIÓN | C5: UNIDAD | D5: CANTIDAD | E5: PRECIO | F5: RENDIMIENTO | G5: TOTAL | H5: % COSTO | I5: TRABAJO | J5: % TIEMPO | K5: Unidades de Recurso Calculado | L5: Unidades de Recurso Asumido
A6: EQUIPOS / HERRAMIENTAS
B7: Herramientas varias | C7: hora | D7: 1 | E7: 0.5 | F7: 4.4 | G7: =ROUND(D7*E7*F7,2) -> 2.2 | H7: =+G7/$G$35 -> 0.02910823 | I7: =+D7*F7 -> 4.4 | J7: =ROUND(F7/$F$34,4) -> 1 | K7: =+D7*J7 -> 1 | L7: =+ROUND(K7,2) -> 1
B10: SUBTOTAL 1 | F10: =SUM(F7:F9) -> 4.4 | G10: =SUM(G7:G9) -> 2.2 | H10: =+G10/$G$35 -> 0.02910823 | I10: =SUM(I7:I9) -> 4.4 | L10: =SUM(L7:L9) -> 1
A11: MATERIALES
B15: SUBTOTAL 2 | G15: =SUM(G12:G14) -> 0 | H15: =+G15/$G$35 -> 0
A16: TRANSPORTE
B17: Transporte en camión capacidad de 200 qq | C17: flete hasta 6km | D17: 1 | E17: 30 | F17: 1 | G17: =+D17*E17*F17 -> 30 | H17: =+G17/$G$35 -> 0.3969304
B20: SUBTOTAL 3 | G20: =SUM(G17:G19) -> 30 | H20: =+G20/$G$35 -> 0.3969304
A21: MANO DE OBRA
B22: Peón | C22: hora | D22: 5 | E22: 3.46 | F22: 2.5 | G22: =ROUND(D22*E22*F22,2) -> 43.25 | H22: =+G22/$G$35 -> 0.57224133 | I22: =+D22*F22 -> 12.5 | J22: =ROUND(F22/$F$34,4) -> 0.5682 | K22: =+D22*J22 -> 2.841 | L22: =+ROUND(K22,2) -> 2.84
B23: Maestro de obra | C23: hora | D23: 1 | E23: 5.11 | F23: 0.025 | G23: =ROUND(D23*E23*F23,2) -> 0.13 | H23: =+G23/$G$35 -> 0.0017200318 | I23: =+D23*F23 -> 0.025 | J23: =ROUND(F23/$F$34,4) -> 0.0057 | K23: =+D23*J23 -> 0.0057 | L23: =+ROUND(K23,2) -> 0.01
B26: SUBTOTAL 4 | D26: =SUM(D22:D24) -> 6 | F26: =SUM(F22:F24) -> 2.525 | G26: =SUM(G22:G24) -> 43.38 | H26: =+G26/$G$35 -> 0.57396137 | I26: =SUM(I22:I24) -> 12.525 | L26: =SUM(L22:L24) -> 2.85
A27: SEGURIDAD INDUSTRIAL
B32: SUBTOTAL 5 | G32: =SUM(G28:G31) -> 0 | H32: =+G32/$G$35 -> 0
E34: DURACIÓN ACTIVIDAD | F34: =+IF(F26>F10,F26,F10) -> 4.4 | G34: Se escoge el mayor rendimiento entre los totales del rendimiento de mano de obra y equipos y herramientas
E35: COSTO DIRECTO | G35: =+G10+G15+G20+G26+G32 -> 75.58
E36: INDIRECTO (12%) | G36: =+ROUND(0.12*G35,2) -> 9.07
E37: COSTO TOTAL | G37: =+G35+G36 -> 84.65

Sheet 1
A1: DESCRIPCIÓN: | B1: Excavación manual, zanja 0-2 m, material sin clasificar | H1: UNIDAD: | I1: m3
A3: RENDIMIENTO: | B3: horas/unidad
A5: CODIGO | B5: DESCRIPCIÓN | C5: UNIDAD | D5: CANTIDAD | E5: PRECIO | F5: RENDIMIENTO | G5: TOTAL | H5: % COSTO | I5: TRABAJO | J5: % TIEMPO | K5: Unidades de Recurso | L5: Unidades de Recurso Asumido
A6: EQUIPOS / HERRAMIENTAS
B7: Herramientas varias | C7: hora | D7: 1 | E7: 0.5 | F7: 2 | G7: =ROUND(D7*E7*F7,2) -> 1 | H7: =+G7/$G$35 -> 0.11185682 | I7: =+D7*F7 -> 2 | J7: =ROUND(F7/$F$34,4) -> 0.9091 | K7: =+D7*J7 -> 0.9091 | L7: =+ROUND(K7,2) -> 0.91
B10: SUBTOTAL 1 | F10: =SUM(F7:F9) -> 2 | G10: =SUM(G7:G9) -> 1 | H10: =+G10/$G$35 -> 0.11185682 | I10: =SUM(I7:I9) -> 2 | K10: =SUM(K7:K9) -> 0.9091 | L10: =SUM(L7:L9) -> 0.91
A11: MATERIALES
L12: la cantidad del presupuesto multiplicado por la cantidad de cada material
B15: SUBTOTAL 2 | G15: =SUM(G12:G14) -> 0 | H15: =+G15/$G$35 -> 0
A16: TRANSPORTE
B20: SUBTOTAL 3 | G20: =SUM(G17:G19) -> 0 | H20: =+G20/$G$35 -> 0
A21: MANO DE OBRA
B22: Peón | C22: hora | D22: 1 | E22: 3.46 | F22: 2 | G22: =ROUND(D22*E22*F22,2) -> 6.92 | H22: =+G22/$G$35 -> 0.77404922 | I22: =+D22*F22 -> 2 | J22: =ROUND(F22/$F$34,4) -> 0.9091 | K22: =+D22*J22 -> 0.9091 | L22: =+ROUND(K22,2) -> 0.91
B23: Maestro de obra | C23: hora | D23: 1 | E23: 5.11 | F23: 0.2 | G23: =ROUND(D23*E23*F23,2) -> 1.02 | H23: =+G23/$G$35 -> 0.11409396 | I23: =+D23*F23 -> 0.2 | J23: =ROUND(F23/$F$34,4) -> 0.0909 | K23: =+D23*J23 -> 0.0909 | L23: =+ROUND(K23,2) -> 0.09
B26: SUBTOTAL 4 | D26: =SUM(D22:D25) -> 2 | F26: =SUM(F22:F25) -> 2.2 | G26: =SUM(G22:G25) -> 7.94 | H26: =+G26/$G$35 -> 0.88814318 | I26: =SUM(I22:I25) -> 2.2 | K26: =SUM(K22:K25) -> 1 | L26: =SUM(L22:L24) -> 1
A27: SEGURIDAD INDUSTRIAL
B32: SUBTOTAL 5 | G32: =SUM(G28:G31) -> 0 | H32: =+G32/$G$35 -> 0
E34: DURACIÓN ACTIVIDAD | F34: =+IF(F26>F10,F26,F10) -> 2.2 | G34: Se escoge el mayor rendimiento entre los totales del rendimiento de mano de obra y equipos y herramientas
E35: COSTO DIRECTO | G35: =+G10+G15+G20+G26+G32 -> 8.94
E36: INDIRECTO (12%) | G36: =+ROUND(0.12*G35,2) -> 1.07
E37: COSTO TOTAL | G37: =+G35+G36 -> 10.01

Sheet 2
A1: DESCRIPCIÓN: | B1: Excavación a máquina con retroexcavadora | H1: UNIDAD: | I1: m3
A3: RENDIMIENTO: | B3: horas/unidad
A5: CODIGO | B5: DESCRIPCIÓN | C5: UNIDAD | D5: CANTIDAD | E5: PRECIO | F5: RENDIMIENTO | G5: TOTAL | H5: % COSTO | I5: TRABAJO | J5: % TIEMPO | K5: Unidades de Recurso | L5: Unidades de Recurso Asumido
A6: EQUIPOS / HERRAMIENTAS
B7: Retroexcavadora | C7: hora | D7: 1 | E7: 20 | F7: 0.0385 | G7: =ROUND(D7*E7*F7,2) -> 0.77 | H7: =+G7/$G$35 -> 0.53472222 | I7: =+D7*F7 -> 0.0385 | J7: =ROUND(F7/$F$34,4) -> 0.2941 | K7: =+D7*J7 -> 0.2941 | L7: =+ROUND(K7,2) -> 0.29
B10: SUBTOTAL 1 | F10: =SUM(F7:F9) -> 0.0385 | G10: =SUM(G7:G9) -> 0.77 | H10: =+G10/$G$35 -> 0.53472222 | I10: =SUM(I7:I9) -> 0.0385 | K10: =SUM(K7:K9) -> 0.2941 | L10: =SUM(L7:L9) -> 0.29
A11: MATERIALES
L12: la cantidad del presupuesto multiplicado por la cantidad de cada material
B15: SUBTOTAL 2 | G15: =SUM(G12:G14) -> 0 | H15: =+G15/$G$35 -> 0
A16: TRANSPORTE
B20: SUBTOTAL 3 | G20: =SUM(G17:G19) -> 0 | H20: =+G20/$G$35 -> 0
A21: MANO DE OBRA
B22: Peón | C22: hora | D22: 2 | E22: 3.46 | F22: 0.0385 | G22: =ROUND(D22*E22*F22,2) -> 0.27 | H22: =+G22/$G$35 -> 0.1875 | I22: =+D22*F22 -> 0.077 | J22: =ROUND(F22/$F$34,4) -> 0.2941 | K22: =+D22*J22 -> 0.5882 | L22: =+ROUND(K22,2) -> 0.59
B23: Albañil | C23: hora | D23: 1 | E23: 4.29 | F23: 0.0385 | G23: =ROUND(D23*E23*F23,2) -> 0.17 | H23: =+G23/$G$35 -> 0.11805556 | I23: =+D23*F23 -> 0.0385 | J23: =ROUND(F23/$F$34,4) -> 0.2941 | K23: =+D23*J23 -> 0.2941 | L23: =+ROUND(K23,2) -> 0.29
B24: Operador | C24: hora | D24: 1 | E24: 3.82 | F24: 0.0385 | G24: =ROUND(D24*E24*F24,2) -> 0.15 | H24: =+G24/$G$35 -> 0.10416667 | I24: =+D24*F24 -> 0.0385 | J24: =ROUND(F24/$F$34,4) -> 0.2941 | K24: =+D24*J24 -> 0.2941 | L24: =+ROUND(K24,2) -> 0.29
B25: Maestro de obra | C25: hora | D25: 1 | E25: 5.11 | F25: 0.0154 | G25: =ROUND(D25*E25*F25,2) -> 0.08 | H25: =+G25/$G$35 -> 0.055555556 | I25: =+D25*F25 -> 0.0154 | J25: =ROUND(F25/$F$34,4) -> 0.1176 | K25: =+D25*J25 -> 0.1176 | L25: =+ROUND(K25,2) -> 0.12
B26: SUBTOTAL 4 | D26: =SUM(D22:D25) -> 5 | F26: =SUM(F22:F25) -> 0.1309 | G26: =SUM(G22:G25) -> 0.67 | H26: =+G26/$G$35 -> 0.46527778 | I26: =SUM(I22:I25) -> 0.1694 | K26: =SUM(K23:K25) -> 0.7058 | L26: =SUM(L22:L25) -> 1.29
A27: SEGURIDAD INDUSTRIAL
B32: SUBTOTAL 5 | G32: =SUM(G28:G31) -> 0 | H32: =+G32/$G$35 -> 0
E34: DURACIÓN ACTIVIDAD | F34: =+IF(F26>F10,F26,F10) -> 0.1309 | G34: Se escoge el mayor rendimiento entre los totales del rendimiento de mano de obra y equipos y herramientas
E35: COSTO DIRECTO | G35: =+G10+G15+G20+G26+G32 -> 1.44
E36: INDIRECTO (12%) | G36: =+ROUND(0.12*G35,2) -> 0.17
E37: COSTO TOTAL | G37: =+G35+G36 -> 1.61

Sheet 3
A1: DESCRIPCIÓN: | B1: Relleno compactado con material de mejoramiento cribado | H1: UNIDAD: | I1: m3
A3: RENDIMIENTO: | B3: horas/unidad
A5: CODIGO | B5: DESCRIPCIÓN | C5: UNIDAD | D5: CANTIDAD | E5: PRECIO | F5: RENDIMIENTO | G5: TOTAL | H5: % COSTO | I5: TRABAJO | J5: % TIEMPO | K5: Unidades de Recurso Calculado | L5: Unidades de Recurso Asumido
A6: EQUIPOS / HERRAMIENTAS
B7: Herramientas varias | C7: hora | D7: 1 | E7: 0.5 | F7: 0.6 | G7: =ROUND(D7*E7*F7,2) -> 0.3 | H7: =+G7/$G$35 -> 0.01183432 | I7: =+D7*F7 -> 0.6 | J7: =ROUND(F7/$F$34,4) -> 0.4545 | K7: =+D7*J7 -> 0.4545 | L7: =+ROUND(K7,2) -> 0.45
B8: Plancha vibratoria | C8: hora | D8: 1 | E8: 3.5 | F8: 0.6 | G8: =ROUND(D8*E8*F8,2) -> 2.1 | H8: =+G8/$G$35 -> 0.082840237 | I8: =+D8*F8 -> 0.6 | J8: =ROUND(F8/$F$34,4) -> 0.4545 | K8: =+D8*J8 -> 0.4545 | L8: =+ROUND(K8,2) -> 0.45
B10: SUBTOTAL 1 | F10: =SUM(F7:F9) -> 1.2 | G10: =SUM(G7:G9) -> 2.4 | H10: =+G10/$G$35 -> 0.094674556 | I10: =SUM(I7:I9) -> 1.2 | L10: =SUM(L7:L9) -> 0.9
A11: MATERIALES
B12: Mejoramiento cribado | C12: m3 | D12: 1.31 | E12: 13.5 | G12: =ROUND(D12*E12,2) -> 17.69 | H12: =+G12/$G$35 -> 0.69783037 | L12: la cantidad del presupuesto multiplicado por la cantidad de cada material
B15: SUBTOTAL 2 | G15: =SUM(G12:G14) -> 17.69 | H15: =+G15/$G$35 -> 0.69783037
A16: TRANSPORTE
B20: SUBTOTAL 3 | G20: =SUM(G17:G19) -> 0 | H20: =+G20/$G$35 -> 0
A21: MANO DE OBRA
B22: Peón | C22: hora | D22: 1 | E22: 3.46 | F22: 0.6 | G22: =ROUND(D22*E22*F22,2) -> 2.08 | H22: =+G22/$G$35 -> 0.082051282 | I22: =+D22*F22 -> 0.6 | J22: =ROUND(F22/$F$34,4) -> 0.4545 | K22: =+D22*J22 -> 0.4545 | L22: =+ROUND(K22,2) -> 0.45
B23: Albañil | C23: hora | D23: 1 | E23: 4.29 | F23: 0.6 | G23: =ROUND(D23*E23*F23,2) -> 2.57 | H23: =+G23/$G$35 -> 0.10138067 | I23: =+D23*F23 -> 0.6 | J23: =ROUND(F23/$F$34,4) -> 0.4545 | K23: =+D23*J23 -> 0.4545 | L23: =+ROUND(K23,2) -> 0.45
B24: Maestro de obra | C24: hora | D24: 1 | E24: 5.11 | F24: 0.12 | G24: =ROUND(D24*E24*F24,2) -> 0.61 | H24: =+G24/$G$35 -> 0.024063116 | I24: =+D24*F24 -> 0.12 | J24: =ROUND(F24/$F$34,4) -> 0.0909 | K24: =+D24*J24 -> 0.0909 | L24: =+ROUND(K24,2) -> 0.09
B26: SUBTOTAL 4 | D26: =SUM(D22:D24) -> 3 | F26: =SUM(F22:F24) -> 1.32 | G26: =SUM(G22:G24) -> 5.26 | H26: =+G26/$G$35 -> 0.20749507 | I26: =SUM(I22:I24) -> 1.32 | L26: =SUM(L22:L24) -> 0.99
A27: SEGURIDAD INDUSTRIAL
B32: SUBTOTAL 5 | G32: =SUM(G28:G31) -> 0 | H32: =+G32/$G$35 -> 0
E34: DURACIÓN ACTIVIDAD | F34: =+IF(F26>F10,F26,F10) -> 1.32 | G34: Se escoge el mayor rendimiento entre los totales del rendimiento de mano de obra y equipos y herramientas
E35: COSTO DIRECTO | G35: =+G10+G15+G20+G26+G32 -> 25.35
E36: INDIRECTO (12%) | G36: =+ROUND(0.12*G35,2) -> 3.04
E37: COSTO TOTAL | G37: =+G35+G36 -> 28.39

Sheet 4(APU)
A1: DESCRIPCIÓN: | B1: Mampostería de bloque e=15cm | H1: UNIDAD: | I1: m2
A3: RENDIMIENTO: | B3: horas/unidad
A5: CODIGO | B5: DESCRIPCIÓN | C5: UNIDAD | D5: CANTIDAD | E5: PRECIO | F5: RENDIMIENTO | G5: TOTAL | H5: % COSTO | I5: TRABAJO | J5: % TIEMPO | K5: Unidades de Recurso Calculado | L5: Unidades de Recurso Asumido
A6: EQUIPOS / HERRAMIENTAS
B7: Herramientas varias | C7: hora | D7: 1 | E7: 0.5 | F7: 0.6 | G7: =ROUND(D7*E7*F7,2) -> 0.3 | H7: =+G7/$G$34 -> 0.021008403 | I7: =+D7*F7 -> 0.6 | J7: =ROUND(F7/$F$33,4) -> 0.4545 | K7: =+D7*J7 -> 0.4545 | L7: =+ROUND(K7,2) -> 0.45
B9: SUBTOTAL 1 | F9: =SUM(F7:F8) -> 0.6 | G9: =SUM(G7:G8) -> 0.3 | H9: =+G9/$G$34 -> 0.021008403 | I9: =SUM(I7:I8) -> 0.6 | L9: =SUM(L7:L8) -> 0.45
A10: MATERIALES
B11: Bloque de 40 × 20 × 15 cm | C11: u | D11: 13 | E11: 0.5 | G11: =ROUND(D11*E11,2) -> 6.5 | H11: =+G11/$G$34 -> 0.45518207 | L11: la cantidad del presupuesto multiplicado por la cantidad de cada material
B12: Mortero de cemento 1:3 | C12: m3 | D12: 0.02 | E12: 110.95 | G12: =ROUND(D12*E12,2) -> 2.22 | H12: =+G12/$G$34 -> 0.15546218
B14: SUBTOTAL 2 | G14: =SUM(G11:G13) -> 8.72 | H14: =+G14/$G$34 -> 0.61064426
A15: TRANSPORTE
B19: SUBTOTAL 3 | G19: =SUM(G16:G18) -> 0 | H19: =+G19/$G$34 -> 0
A20: MANO DE OBRA
B21: Peón | C21: hora | D21: 1 | E21: 3.46 | F21: 0.6 | G21: =ROUND(D21*E21*F21,2) -> 2.08 | H21: =+G21/$G$34 -> 0.14565826 | I21: =+D21*F21 -> 0.6 | J21: =ROUND(F21/$F$33,4) -> 0.4545 | K21: =+D21*J21 -> 0.4545 | L21: =+ROUND(K21,2) -> 0.45
B22: Albañil | C22: hora | D22: 1 | E22: 4.29 | F22: 0.6 | G22: =ROUND(D22*E22*F22,2) -> 2.57 | H22: =+G22/$G$34 -> 0.17997199 | I22: =+D22*F22 -> 0.6 | J22: =ROUND(F22/$F$33,4) -> 0.4545 | K22: =+D22*J22 -> 0.4545 | L22: =+ROUND(K22,2) -> 0.45
B23: Maestro de obra | C23: hora | D23: 1 | E23: 5.11 | F23: 0.12 | G23: =ROUND(D23*E23*F23,2) -> 0.61 | H23: =+G23/$G$34 -> 0.042717087 | I23: =+D23*F23 -> 0.12 | J23: =ROUND(F23/$F$33,4) -> 0.0909 | K23: =+D23*J23 -> 0.0909 | L23: =+ROUND(K23,2) -> 0.09
B25: SUBTOTAL 4 | D25: =SUM(D21:D23) -> 3 | F25: =SUM(F21:F23) -> 1.32 | G25: =SUM(G21:G23) -> 5.26 | H25: =+G25/$G$34 -> 0.36834734 | I25: =SUM(I21:I23) -> 1.32 | L25: =SUM(L21:L23) -> 0.99
A26: SEGURIDAD INDUSTRIAL
B31: SUBTOTAL 5 | G31: =SUM(G27:G30) -> 0 | H31: =+G31/$G$34 -> 0
E33: DURACIÓN ACTIVIDAD | F33: =+IF(F25>F9,F25,F9) -> 1.32 | G33: Se escoge el mayor rendimiento entre los totales del rendimiento de mano de obra y equipos y herramientas
E34: COSTO DIRECTO | G34: =+G9+G14+G19+G25+G31 -> 14.28
E35: INDIRECTO (12%) | G35: =+ROUND(0.12*G34,2) -> 1.71
E36: COSTO TOTAL | G36: =+G34+G35 -> 15.99

Sheet 4(APU anidado)
A1: DESCRIPCIÓN: | B1: Mortero de cemento 1:3 | H1: UNIDAD: | I1: m3
A3: RENDIMIENTO: | B3: horas/unidad
A5: CODIGO | B5: DESCRIPCIÓN | C5: UNIDAD | D5: CANTIDAD | E5: PRECIO | F5: RENDIMIENTO | G5: TOTAL | H5: % COSTO | I5: TRABAJO | J5: % TIEMPO | K5: Unidades de Recurso Calculado | L5: Unidades de Recurso Asumido
A6: EQUIPOS / HERRAMIENTAS
B7: Herramientas varias | C7: hora | D7: 2 | E7: 0.5 | F7: 0.9 | G7: =ROUND(D7*E7*F7,2) -> 0.9 | H7: =+G7/$G$34 -> 0.0081117621 | I7: =+D7*F7 -> 1.8 | J7: =ROUND(F7/$F$33,4) -> 0.4348 | K7: =+D7*J7 -> 0.8696 | L7: =+ROUND(K7,2) -> 0.87
B9: SUBTOTAL 1 | F9: =SUM(F7:F8) -> 0.9 | G9: =SUM(G7:G8) -> 0.9 | H9: =+G9/$G$34 -> 0.0081117621 | I9: =SUM(I7:I8) -> 1.8 | L9: =SUM(L7:L8) -> 0.87
A10: MATERIALES
B11: Cemento | C11: saco | D11: 10 | E11: 7.25 | G11: =ROUND(D11*E11,2) -> 72.5 | H11: =+G11/$G$34 -> 0.6534475 | L11: la cantidad del presupuesto multiplicado por la cantidad de cada material
B12: Arena | C12: m3 | D12: 1.15 | E12: 20.5 | G12: =ROUND(D12*E12,2) -> 23.58 | H12: =+G12/$G$34 -> 0.21252817
B13: Agua | C13: l | D13: 250 | E13: 0.01 | G13: =ROUND(D13*E13,2) -> 2.5 | H13: =+G13/$G$34 -> 0.022532672
B14: SUBTOTAL 2 | G14: =SUM(G11:G13) -> 98.58 | H14: =+G14/$G$34 -> 0.88850834
A15: TRANSPORTE
B19: SUBTOTAL 3 | G19: =SUM(G16:G18) -> 0 | H19: =+G19/$G$34 -> 0
A20: MANO DE OBRA
B21: Peón | C21: hora | D21: 2 | E21: 3.46 | F21: 0.9 | G21: =ROUND(D21*E21*F21,2) -> 6.23 | H21: =+G21/$G$34 -> 0.05615142 | I21: =+D21*F21 -> 1.8 | J21: =ROUND(F21/$F$33,4) -> 0.4348 | K21: =+D21*J21 -> 0.8696 | L21: =+ROUND(K21,2) -> 0.87
B22: Albañil | C22: hora | D22: 1 | E22: 4.29 | F22: 0.9 | G22: =ROUND(D22*E22*F22,2) -> 3.86 | H22: =+G22/$G$34 -> 0.034790446 | I22: =+D22*F22 -> 0.9 | J22: =ROUND(F22/$F$33,4) -> 0.4348 | K22: =+D22*J22 -> 0.4348 | L22: =+ROUND(K22,2) -> 0.43
B23: Maestro de obra | C23: hora | D23: 1 | E23: 5.11 | F23: 0.27 | G23: =ROUND(D23*E23*F23,2) -> 1.38 | H23: =+G23/$G$34 -> 0.012438035 | I23: =+D23*F23 -> 0.27 | J23: =ROUND(F23/$F$33,4) -> 0.1304 | K23: =+D23*J23 -> 0.1304 | L23: =+ROUND(K23,2) -> 0.13
B25: SUBTOTAL 4 | D25: =SUM(D21:D23) -> 4 | F25: =SUM(F21:F23) -> 2.07 | G25: =SUM(G21:G23) -> 11.47 | H25: =+G25/$G$34 -> 0.1033799 | I25: =SUM(I21:I23) -> 2.97 | L25: =SUM(L21:L23) -> 1.43
A26: SEGURIDAD INDUSTRIAL
B31: SUBTOTAL 5 | G31: =SUM(G27:G30) -> 0 | H31: =+G31/$G$34 -> 0
E33: DURACIÓN ACTIVIDAD | F33: =+IF(F25>F9,F25,F9) -> 2.07 | G33: Se escoge el mayor rendimiento entre los totales del rendimiento de mano de obra y equipos y herramientas
E34: COSTO DIRECTO | G34: =+G9+G14+G19+G25+G31 -> 110.95
E35: INDIRECTO (12%) | G35: =+ROUND(0.12*G34,2) -> 13.31
E36: COSTO TOTAL | G36: =+G34+G35 -> 124.26

Sheet 4(APU anidado con cantidad)
A1: DESCRIPCIÓN: | B1: Mortero de cemento 1:3 | H1: UNIDAD: | I1: m3
A3: RENDIMIENTO: | B3: horas/unidad
A5: CODIGO | B5: DESCRIPCIÓN | C5: UNIDAD | D5: CANTIDAD | E5: PRECIO | F5: RENDIMIENTO | G5: TOTAL | H5: % COSTO | I5: TRABAJO | J5: % TIEMPO | K5: Unidades de Recurso Calculado | L5: Unidades de Recurso Asumido
A6: EQUIPOS / HERRAMIENTAS
B7: Herramientas varias | C7: hora | D7: 2 | E7: 0.5 | F7: =0.9*'4(APU)'!D12 -> 0.018 | G7: =ROUND(D7*E7*F7,2) -> 0.02 | H7: =+G7/$G$34 -> 0.009009009 | I7: =+D7*F7 -> 0.036 | J7: =ROUND(F7/$F$33,4) -> 0.4348 | K7: =+D7*J7 -> 0.8696 | L7: =+ROUND(K7,2) -> 0.87
B9: SUBTOTAL 1 | F9: =SUM(F7:F8) -> 0.018 | G9: =SUM(G7:G8) -> 0.02 | H9: =+G9/$G$34 -> 0.009009009 | I9: =SUM(I7:I8) -> 0.036 | L9: =SUM(L7:L8) -> 0.87
A10: MATERIALES
B11: Cemento | C11: saco | D11: =10*'4(APU)'!D12 -> 0.2 | E11: 7.25 | G11: =ROUND(D11*E11,2) -> 1.45 | H11: =+G11/$G$34 -> 0.65315315 | L11: la cantidad del presupuesto multiplicado por la cantidad de cada material
B12: Arena | C12: m3 | D12: =1.15*'4(APU)'!$D$12 -> 0.023 | E12: 20.5 | G12: =ROUND(D12*E12,2) -> 0.47 | H12: =+G12/$G$34 -> 0.21171171
B13: Agua | C13: l | D13: =250*'4(APU)'!$D$12 -> 5 | E13: 0.01 | G13: =ROUND(D13*E13,2) -> 0.05 | H13: =+G13/$G$34 -> 0.022522523
B14: SUBTOTAL 2 | G14: =SUM(G11:G13) -> 1.97 | H14: =+G14/$G$34 -> 0.88738739
A15: TRANSPORTE
B19: SUBTOTAL 3 | G19: =SUM(G16:G18) -> 0 | H19: =+G19/$G$34 -> 0
A20: MANO DE OBRA
B21: Peón | C21: hora | D21: 2 | E21: 3.46 | F21: =0.9*'4(APU)'!D12 -> 0.018 | G21: =ROUND(D21*E21*F21,2) -> 0.12 | H21: =+G21/$G$34 -> 0.054054054 | I21: =+D21*F21 -> 0.036 | J21: =ROUND(F21/$F$33,4) -> 0.4348 | K21: =+D21*J21 -> 0.8696 | L21: =+ROUND(K21,2) -> 0.87
B22: Albañil | C22: hora | D22: 1 | E22: 4.29 | F22: =0.9*'4(APU)'!D12 -> 0.018 | G22: =ROUND(D22*E22*F22,2) -> 0.08 | H22: =+G22/$G$34 -> 0.036036036 | I22: =+D22*F22 -> 0.018 | J22: =ROUND(F22/$F$33,4) -> 0.4348 | K22: =+D22*J22 -> 0.4348 | L22: =+ROUND(K22,2) -> 0.43
B23: Maestro de obra | C23: hora | D23: 1 | E23: 5.11 | F23: =0.27*'4(APU)'!D12 -> 0.0054 | G23: =ROUND(D23*E23*F23,2) -> 0.03 | H23: =+G23/$G$34 -> 0.013513514 | I23: =+D23*F23 -> 0.0054 | J23: =ROUND(F23/$F$33,4) -> 0.1304 | K23: =+D23*J23 -> 0.1304 | L23: =+ROUND(K23,2) -> 0.13
B25: SUBTOTAL 4 | D25: =SUM(D21:D23) -> 4 | F25: =SUM(F21:F23) -> 0.0414 | G25: =SUM(G21:G23) -> 0.23 | H25: =+G25/$G$34 -> 0.1036036 | I25: =SUM(I21:I23) -> 0.0594 | L25: =SUM(L21:L23) -> 1.43
A26: SEGURIDAD INDUSTRIAL
B31: SUBTOTAL 5 | G31: =SUM(G27:G30) -> 0 | H31: =+G31/$G$34 -> 0
E33: DURACIÓN ACTIVIDAD | F33: =+IF(F25>F9,F25,F9) -> 0.0414 | G33: Se escoge el mayor rendimiento entre los totales del rendimiento de mano de obra y equipos y herramientas
E34: COSTO DIRECTO | G34: =+G9+G14+G19+G25+G31 -> 2.22 | H34: Debe verificarse que este valor sea igual al que está en el precio unitario principal
E35: INDIRECTO (12%) | G35: =+ROUND(0.12*G34,2) -> 0.27
E36: COSTO TOTAL | G36: =+G34+G35 -> 2.49

Sheet 4(APU unificado)
A1: DESCRIPCIÓN: | B1: Mampostería de bloque e=15cm | H1: UNIDAD: | I1: m2
A3: RENDIMIENTO: | B3: horas/unidad
A5: CODIGO | B5: DESCRIPCIÓN | C5: UNIDAD | D5: CANTIDAD | E5: PRECIO | F5: RENDIMIENTO | G5: TOTAL | H5: % COSTO | I5: TRABAJO | J5: % TIEMPO | K5: Unidades de Recurso Calculado | L5: Unidades de Recurso Asumido
A6: EQUIPOS / HERRAMIENTAS
B7: Herramientas varias | C7: hora | D7: =1+'4(APU anidado con cantidad)'!D7 -> 3 | E7: 0.5 | F7: =+G7/D7/E7 -> 0.21333333 | G7: =+'4(APU)'!G7+'4(APU anidado con cantidad)'!G7 -> 0.32 | H7: =+G7/$G$35 -> 0.022408964 | I7: =+D7*F7 -> 0.64 | J7: =ROUND(F7/$F$34,4) -> 0.3657 | K7: =+D7*J7 -> 1.0971 | L7: =+ROUND(K7,2) -> 1.1
B9: SUBTOTAL 1 | F9: =SUM(F7:F8) -> 0.21333333 | G9: =SUM(G7:G8) -> 0.32 | H9: =+G9/$G$35 -> 0.022408964 | I9: =SUM(I7:I8) -> 0.64 | L9: =SUM(L7:L8) -> 1.1
A10: MATERIALES
B11: Bloque de 40 × 20 × 15 cm | C11: u | D11: =+'4(APU)'!D11 -> 13 | E11: 0.5 | G11: =ROUND(D11*E11,2) -> 6.5 | H11: =+G11/$G$35 -> 0.45518207
B12: Cemento | C12: saco | D12: =10*'4(APU)'!D12 -> 0.2 | E12: 7.25 | G12: =ROUND(D12*E12,2) -> 1.45 | H12: =+G12/$G$35 -> 0.10154062 | L12: la cantidad del presupuesto multiplicado por la cantidad de cada material
B13: Arena | C13: m3 | D13: =1.15*'4(APU)'!$D$12 -> 0.023 | E13: 20.5 | G13: =ROUND(D13*E13,2) -> 0.47 | H13: =+G13/$G$35 -> 0.032913165
B14: Agua | C14: l | D14: =250*'4(APU)'!$D$12 -> 5 | E14: 0.01 | G14: =ROUND(D14*E14,2) -> 0.05 | H14: =+G14/$G$35 -> 0.0035014006
B15: SUBTOTAL 2 | G15: =SUM(G11:G14) -> 8.47 | H15: =+G15/$G$35 -> 0.59313725
A16: TRANSPORTE
B20: SUBTOTAL 3 | G20: =SUM(G17:G19) -> 0 | H20: =+G20/$G$35 -> 0
A21: MANO DE OBRA
B22: Peón | C22: hora | D22: =+'4(APU)'!D21+'4(APU anidado con cantidad)'!D21 -> 3 | E22: 3.46 | F22: =+G22/D22/E22 -> 0.21194605 | G22: =+'4(APU)'!G21+'4(APU anidado con cantidad)'!G21 -> 2.2 | H22: =+G22/$G$35 -> 0.15406162 | I22: =+D22*F22 -> 0.63583815 | J22: =ROUND(F22/$F$34,4) -> 0.3633 | K22: =+D22*J22 -> 1.0899 | L22: =+ROUND(K22,2) -> 1.09
B23: Albañil | C23: hora | D23: =+'4(APU)'!D22+'4(APU anidado con cantidad)'!D22 -> 2 | E23: 4.29 | F23: =+G23/D23/E23 -> 0.30885781 | G23: =+'4(APU)'!G22+'4(APU anidado con cantidad)'!G22 -> 2.65 | H23: =+G23/$G$35 -> 0.18557423 | I23: =+D23*F23 -> 0.61771562 | J23: =ROUND(F23/$F$34,4) -> 0.5294 | K23: =+D23*J23 -> 1.0588 | L23: =+ROUND(K23,2) -> 1.06
B24: Maestro de obra | C24: hora | D24: =+'4(APU)'!D23+'4(APU anidado con cantidad)'!D23 -> 2 | E24: 5.11 | F24: =+G24/D24/E24 -> 0.062622309 | G24: =+'4(APU)'!G23+'4(APU anidado con cantidad)'!G23 -> 0.64 | H24: =+G24/$G$35 -> 0.044817927 | I24: =+D24*F24 -> 0.12524462 | J24: =ROUND(F24/$F$34,4) -> 0.1073 | K24: =+D24*J24 -> 0.2146 | L24: =+ROUND(K24,2) -> 0.21
B26: SUBTOTAL 4 | D26: =SUM(D22:D24) -> 7 | F26: =SUM(F22:F24) -> 0.58342617 | G26: =SUM(G22:G24) -> 5.49 | H26: =+G26/$G$35 -> 0.38445378 | I26: =ROUND(SUM(I22:I24),2) -> 1.38 | L26: =SUM(L22:L24) -> 2.36
A27: SEGURIDAD INDUSTRIAL
B32: SUBTOTAL 5 | G32: =SUM(G28:G31) -> 0 | H32: =+G32/$G$35 -> 0
E34: DURACIÓN ACTIVIDAD | F34: =+IF(F26>F9,F26,F9) -> 0.58342617 | G34: Se escoge el mayor rendimiento entre los totales del rendimiento de mano de obra y equipos y herramientas
E35: COSTO DIRECTO | G35: =+G9+G15+G20+G26+G32 -> 14.28 | H35: Debe verificarse que este valor sea igual al que está en el precio unitario principal
E36: INDIRECTO (12%) | G36: =+ROUND(0.12*G35,2) -> 1.71
E37: COSTO TOTAL | G37: =+G35+G36 -> 15.99

Sheet 5
A1: DESCRIPCIÓN: | B1: Transporte de materiales hasta 6 km, incluye pago en escombrera | H1: UNIDAD: | I1: m3
A3: RENDIMIENTO: | B3: horas/unidad
A5: CODIGO | B5: DESCRIPCIÓN | C5: UNIDAD | D5: CANTIDAD | E5: PRECIO | F5: RENDIMIENTO | G5: TOTAL | H5: % COSTO | I5: TRABAJO | J5: % TIEMPO | K5: Unidades de Recurso Calculado | L5: Unidades de Recurso Asumido
A6: EQUIPOS / HERRAMIENTAS
B7: Volqueta 8m3 | C7: hora | D7: 1 | E7: 20 | F7: 0.02 | G7: =ROUND(D7*E7*F7,2) -> 0.4 | H7: =+G7/$G$35 -> 0.44444444 | I7: =+D7*F7 -> 0.02 | J7: =ROUND(F7/$F$34,4) -> 1 | K7: =+D7*J7 -> 1 | L7: =+ROUND(K7,2) -> 1
B10: SUBTOTAL 1 | F10: =SUM(F7:F9) -> 0.02 | G10: =SUM(G7:G9) -> 0.4 | H10: =+G10/$G$35 -> 0.44444444 | I10: =SUM(I7:I9) -> 0.02 | L10: =SUM(L7:L9) -> 1
A11: MATERIALES
B12: Pago por concepto de disposición de materiales en escombrera | C12: m3 | D12: 1 | E12: 0.4 | G12: =ROUND(D12*E12,2) -> 0.4 | H12: =+G12/$G$35 -> 0.44444444 | L12: la cantidad del presupuesto multiplicado por la cantidad de cada material
B15: SUBTOTAL 2 | G15: =SUM(G12:G14) -> 0.4 | H15: =+G15/$G$35 -> 0.44444444
A16: TRANSPORTE
B20: SUBTOTAL 3 | G20: =SUM(G17:G19) -> 0 | H20: =+G20/$G$35 -> 0
A21: MANO DE OBRA
B22: Chofer de volqueta | C22: hora | D22: 1 | E22: 5 | F22: 0.02 | G22: =ROUND(D22*E22*F22,2) -> 0.1 | H22: =+G22/$G$35 -> 0.11111111 | I22: =+D22*F22 -> 0.02 | J22: =ROUND(F22/$F$34,4) -> 1 | K22: =+D22*J22 -> 1 | L22: =+ROUND(K22,2) -> 1
B26: SUBTOTAL 4 | D26: =SUM(D22:D24) -> 1 | F26: =SUM(F22:F24) -> 0.02 | G26: =SUM(G22:G24) -> 0.1 | H26: =+G26/$G$35 -> 0.11111111 | I26: =SUM(I22:I24) -> 0.02 | L26: =SUM(L22:L24) -> 1
A27: SEGURIDAD INDUSTRIAL
B32: SUBTOTAL 5 | G32: =SUM(G28:G31) -> 0 | H32: =+G32/$G$35 -> 0
E34: DURACIÓN ACTIVIDAD | F34: =+IF(F26>F10,F26,F10) -> 0.02 | G34: Se escoge el mayor rendimiento entre los totales del rendimiento de mano de obra y equipos y herramientas
E35: COSTO DIRECTO | G35: =+G10+G15+G20+G26+G32 -> 0.9
E36: INDIRECTO (12%) | G36: =+ROUND(0.12*G35,2) -> 0.11
E37: COSTO TOTAL | G37: =+G35+G36 -> 1.01
